src/design/7SEG.SV
module display (
    input logic clk,
    input logic clk_div,
    input logic load_num,
    input logic [15:0] num,
    output logic [4:0] anodos,
    output logic [6:0] segmentos
);

    reg [2:0] select, next_select;
    reg [3:0] digito, next_digito;

    parameter sel0 = 3'b000, sel1 = 3'b001, sel2 = 3'b010, sel3 = 3'b011, sel4 = 3'b100;

    always_ff @(posedge clk) begin
        select <= next_select;
        digito <= next_digito;
    end

    //controla activar un display a la vez
    always @ (posedge clk) begin
        case (select) // traduce c/d numero BCD al 7seg correspondiente
            sel0: begin
                anodos = 5'b00001; // Activar display 1
                next_select = sel1;
                next_digito = num[3:0];
            end

            sel1: begin
                anodos = 5'b00010; // Activar display 2
                next_select = sel2;
                next_digito = num[7:4];
            end

            sel2: begin
                anodos = 5'b00100; // Activar display 3
                next_select = sel3;
                next_digito = num[11:8];
            end

            sel3: begin 
                anodos = 5'b01000; // Activar display 4
                next_select = sel4;
                next_digito = num[15:12];
            end
            
            sel4: begin
                anodos = 5'b10000;
                next_select = sel0;
                next_digito = 0;
            end

            default: begin
                anodos = 5'b00000;
                next_select = sel0;
                next_digito = num[3:0];
            end
        endcase  
    end

    // controla el segmentos de acuerdo con el digito BCD
    always_comb begin
        case(digito)
            4'd0: segmentos = 7'b0111111; // 0
            4'd1: segmentos = 7'b0000110; // 1
            4'd2: segmentos = 7'b1011011; // 2
            4'd3: segmentos = 7'b1001111; // 3
            4'd4: segmentos = 7'b1100110; // 4
            4'd5: segmentos = 7'b1101101; // 5
            4'd6: segmentos = 7'b1111101; // 6
            4'd7: segmentos = 7'b0000111; // 7
            4'd8: segmentos = 7'b1111111; // 8
            4'd9: segmentos = 7'b1101111; // 9
            default: segmentos = 7'b1111111; // Desactiva los segmentos
        endcase
    end

endmodule

src/design/Conv-BCD.sv
module bin_decimal ( //usando el algoritmo de doble dabble
    input [15:0] binario, //13 bits para manejar el acarreo
    output reg [15:0] bcd// salida BCD 4 digitos
);

    integer i;
    always @ (binario) begin
        bcd = 16'b0;  // Inicializar BCD a 0
        for (i = 0; i < 15; i = i + 1) begin
            // Si cualquier grupo de 4 bits en BCD es mayor o igual a 5, suma 3
            if (bcd[3:0] >= 5) bcd[3:0] = bcd[3:0] + 3;
            if (bcd[7:4] >= 5) bcd[7:4] = bcd[7:4] + 3;
            if (bcd[11:8] >= 5) bcd[11:8] = bcd[11:8] + 3;
            if (bcd[15:12] >= 5) bcd[15:12] = bcd[15:12] + 3;

            bcd = {bcd[14:0], binario[15-i]}; // desplaza los bits del binario
        end
    end

endmodule

src/design/mult_datapath.sv
/*typedef struct {
    logic load_A ;
    logic load_B ;
    logic load_add ;
    logic shift_HQ_LQ_Q_1 ;
    logic add_sub ;
} mult_control_t ;*/

module mult_with_no_fsm #(
    parameter n = 8
    ) (
    input logic clk ,
    input logic rst ,
    input logic [n-1:0] a,
    input logic [n-1:0] b,
    //input mult_control_t mult_control ,
    input logic load_A,
    input logic load_B,
    input logic load_add,
    input logic shift_HQ_LQ_Q_1,
    input logic add_sub,
    output logic [1:0] q_LSB,
    output logic [2*n-1:0] y
) ;


logic [n-1:0] m;
logic [n-1:0] adder_sub_out ;
logic [2*n: 0 ] shift ;
logic [n-1:0] hq;
logic [n-1:0] lq;
logic q_1;

//reg_M
always_ff@ (posedge clk , posedge rst ) begin
    if ( rst )
        m <='b0 ;
    else
        m <= (/*mult_control.*/load_A) ? a : m;
    end

// adder / sub
always_comb begin
    if (/*mult_control.*/add_sub )
        adder_sub_out = m + hq;
    else
        adder_sub_out = m - hq;
    end
// shift registers
always_comb begin
    y = {hq,lq} ;
    hq = shift[2*n:n+1];
    lq = shift[n:1] ;
    q_1 = shift[0] ;
    q_LSB = {lq[0] ,q_1} ;
end


always_ff@ (posedge clk , posedge rst ) begin
    if ( rst )
        shift <= 'b0 ;
    else if (/*mult_control.*/shift_HQ_LQ_Q_1)
        // arithmetic shift
        shift <= $signed (shift)>>>1;
         else begin
            if ( /*mult_control.*/load_B )
                shift [n:1] <= b;
            if ( /*mult_control.*/load_add )
                shift [2*n:n+1] <= adder_sub_out ;
        end
    end


endmodule

src/design/mult_control.sv
/*typedef struct {
    logic load_A ;
    logic load_B ;
    logic load_add ;
    logic shift_HQ_LQ_Q_1 ;
    logic add_sub ;
} mult_control_t ;*/

module control #(
    parameter n = 8
    ) (
    input logic clk,
    input logic rst,
    input logic signal_num,
    input logic [1:0] q_LSB,
    //output mult_control_t mult_control
    output logic load_A,
    output logic load_B,
    output logic load_add,
    output logic shift_HQ_LQ_Q_1,
    output logic add_sub
    );

    reg [6:0] state, next_state;
    reg [2:0] cont;
    reg [1:0] z;

    parameter idle = 7'b0000001, init = 7'b0000010, sel0 = 7'b0000100; 
    parameter sum = 7'b0001000, res = 7'b0010000, shift = 7'b0100000, sel1 = 7'b1000000;

    always_ff @(posedge clk) begin
        if (rst) begin
            cont <= 3'b111;
            state <= idle;
        end
        else begin
            state <= next_state;
        end
    end

    always_comb begin
        case (state)
            idle: begin
                if (signal_num) begin
                    next_state = init;
                end
                else begin
                    next_state = idle;
                end
            end

            init: begin
                cont = 3'b111;
                /*mult_control.*/load_A = 1'b1;
                /*mult_control.*/load_B = 1'b1;
                /*mult_control.*/load_add = 0;
                /*mult_control.*/shift_HQ_LQ_Q_1 = 0;
                /*mult_control.*/add_sub = 0;
                next_state = sel0;
            end

            sel0: begin
                cont = 3'b111;
                /*mult_control.*/load_A = 0;
                /*mult_control.*/load_B = 0;
                /*mult_control.*/load_add = 0;
                /*mult_control.*/shift_HQ_LQ_Q_1 = 1'b1;
                /*mult_control.*/add_sub = 0;
                if (q_LSB[0] == q_LSB[1]) begin
                    next_state = shift;
                end
                else if (q_LSB[0]) begin
                    next_state = sum;
                end
                else if (q_LSB[1]) begin
                    next_state = res;
                end
            end

            sum: begin
                cont = 3'b111;
                /*mult_control.*/load_A = 0;
                /*mult_control.*/load_B = 0;
                /*mult_control.*/load_add = 1'b1;
                /*mult_control.*/shift_HQ_LQ_Q_1 = 0;
                /*mult_control.*/add_sub = 1'b1;
                next_state = shift;
            end

            res: begin
                cont = 3'b111;
                /*mult_control.*/load_A = 0;
                /*mult_control.*/load_B = 0;
                /*mult_control.*/load_add = 1'b1;
                /*mult_control.*/shift_HQ_LQ_Q_1 = 0;
                /*mult_control.*/add_sub = 0;
                next_state = shift;
            end

            shift: begin
                cont = cont - 1'b1;
                if (cont == 0) begin
                    z = 1'b1;
                end
                else begin
                    z = 0;
                end
                next_state = sel1;
            end

            sel1: begin
                if (z) begin
                    next_state = idle;
                end
                else begin
                    next_state = sel0;
                end
            end

            default: begin
                cont = 3'b111;
                /*mult_control.*/load_A = 0;
                /*mult_control.*/load_B = 0;
                /*mult_control.*/load_add = 0;
                /*mult_control.*/shift_HQ_LQ_Q_1 = 0;
                /*mult_control.*/add_sub = 0;
                next_state = idle;
            end
        endcase
    end

endmodule

src/design/Numero.sv
module Numeros (
    input logic clk,
    input logic rst,
    input logic [3:0] num,
    input logic load_num,

    output logic [7:0] num_o,
    output logic [7:0] num_A, 
    output logic [7:0] num_B,
    output logic signal_num
);

    reg [2:0] state, next_state;
    logic [7:0] num_parcial;

    parameter s0 = 3'b000, s1 = 3'b001, s2 = 3'b010, s3 = 3'b011; 
    parameter s4 = 3'b100, s5 = 3'b101, s6 = 3'b110;
    parameter enter = 4'b1011, delete = 4'b1100;
    
    always_ff @(posedge clk) begin
        if (rst) begin
            state <= s0;
        end
        else if (load_num) begin
            state <= next_state;
        end
    end

    always @ (posedge clk) begin
        num_o = 0;
        num_parcial = 0;
        signal_num = 0;
        num_A = 0;
        num_B = 0;
        case (state)
            s0: begin
                num_o = 0;
                num_parcial = 0;
                signal_num = 0;
                if (load_num) begin
                    if (num == enter) begin
                        num_A = 0;
                        next_state = s3;
                    end
                    else if (num == delete) begin
                        next_state = s0;
                    end
                    else begin
                        num_o = num;
                        num_parcial = num;
                        next_state = s1;
                    end
                end
                else begin
                    next_state = s0;
                end
            end

            s1: begin
                if (load_num) begin
                    if (num == enter) begin
                        num_A = num_parcial;
                        next_state = s3;
                    end
                    else if (num == delete) begin
                        num_o = 0;
                        num_parcial = 0;
                        next_state = s0;
                    end
                    else begin
                        num_o = {num_parcial[7:4], num};
                        num_parcial = num_parcial*4'b1010 + num;
                        next_state = s2;
                    end
                end
                else begin
                    next_state = s1;
                end
            end

            s2: begin
                if (load_num) begin
                    if (num == enter) begin
                        num_A = num_parcial;
                        next_state = s3;
                    end
                    else if (num == delete) begin
                        num_o = {4'b0000, num_o[7:4]};
                        num_parcial = num_o;
                        next_state = s1;
                    end
                    else begin
                        next_state = s2;
                    end
                end
                else begin
                    next_state = s2;
                end
            end

            s3: begin
                if (load_num) begin
                    if (num == enter) begin
                        num_B = 0;
                        next_state = s6;
                        signal_num = 1;
                    end
                    else if (num == delete) begin
                        next_state = s3;
                    end
                    else begin
                        num_o = num;
                        num_parcial = num;
                        next_state = s4;
                    end
                end
                else begin
                    next_state = s3;
                end
            end

            s4: begin
                if (load_num) begin
                    if (num == enter) begin
                        num_B = num_parcial;
                        next_state = s6;
                        signal_num = 1;
                    end
                    else if (num == delete) begin
                        num_o = 0;
                        num_parcial = 0;
                        next_state = s3;
                    end
                    else begin
                        num_o = {num_parcial[7:4], num};
                        num_parcial = num_parcial*4'b1010 + num;
                        next_state = s5;
                    end
                end
                else begin
                    next_state = s4;
                end
            end

            s5: begin
                if (load_num) begin
                    if (num == enter) begin
                        num_B = num_parcial;
                        next_state = s6;
                        signal_num = 1;
                    end
                    else if (num == delete) begin
                        num_o = {4'b0000, num_o};
                        num_parcial = num_o;
                        next_state = s4;
                    end
                    else begin
                        next_state = s5;
                    end
                end
                else begin
                    next_state = s5;
                end
            end

            s6: begin
                if (load_num) begin
                    if (num == enter) begin
                        signal_num = 0;
                        next_state = s0;
                    end
                    else begin
                        next_state = s6;
                    end
                end
                else begin
                    next_state = s6;
                end
            end

            default: begin
                next_state = s0;
                num_o = 0;
                num_parcial = 0;
                signal_num = 0;
                num_A = 0;
                num_B = 0;
            end

        endcase
    end

endmodule

src/design/Teclado.sv
module Teclado (
    input logic rst,
    input logic clk_div,
    input logic [3:0] sync_row,
    output logic [3:0] col,
    output logic [3:0] num,
    output logic load_num
);

    reg [5:0] state, next_state;
    reg sum_row;

    parameter state0 = 6'b000001, state1 = 6'b000010, state2 = 6'b000100;
    parameter state3 = 6'b001000, state4 = 6'b010000, state5 = 6'b100000;

    always @(sync_row or col) begin
        case ({sync_row, col})
            {4'b0001, 4'b0001}: num = 4'b0000; //0
            {4'b0001, 4'b0010}: num = 4'b0001; //1
            {4'b0001, 4'b0100}: num = 4'b0010; //2
            {4'b0001, 4'b1000}: num = 4'b0011; //3
            {4'b0010, 4'b0001}: num = 4'b0100; //4
            {4'b0010, 4'b0010}: num = 4'b0101; //5
            {4'b0010, 4'b0100}: num = 4'b0110; //6
            {4'b0010, 4'b1000}: num = 4'b0111; //7
            {4'b0100, 4'b0001}: num = 4'b1000; //8
            {4'b0100, 4'b0010}: num = 4'b1001; //9
            {4'b0100, 4'b0100}: num = 4'b1010; //A - Signo Negativo
            {4'b0100, 4'b1000}: num = 4'b1011; //B - Intro
            {4'b1000, 4'b0001}: num = 4'b1100; //C - Borrar
            //{4'b1000, 4'b0010}: num = 4'b1101; //D
            //{4'b1000, 4'b0100}: num = 4'b1110; //#
            //{4'b1000, 4'b1000}: num = 4'b1111; //*
            default: num = 4'b0000;
        endcase
    end

    always_ff @(posedge clk_div) begin
        if (rst) begin
            state <= state0;
        end
        else begin
            state <= next_state;
        end
    end

    always @ (state or sync_row) begin
        next_state = state;
        col = 4'b0000;
        sum_row = sync_row[3] || sync_row[2] || sync_row[1] || sync_row[0];
        case (state)
            state0:
                begin
                    col = 4'b1111;
                    load_num = 0;
                    if (sum_row) begin
                        next_state = state1;
                    end
                    else begin
                        next_state = state0;
                    end
                end
                
            state1:
                begin
                    col = 4'b0001;
                    if (sync_row) begin
                        next_state = state5;
                        load_num = 1'b1;
                    end
                    else begin
                        next_state = state2;
                    end
                end
                
            state2:
                begin
                    col = 4'b0010;
                    if (sync_row) begin
                        next_state = state5;
                        load_num = 1'b1;
                    end
                    else begin
                        next_state = state3;
                    end
                end
                
            state3:
                begin
                    col = 4'b0100;
                    if (sync_row) begin
                        next_state = state5;
                        load_num = 1'b1;
                    end
                    else begin
                        next_state = state4;
                    end
                end

            state4:
                begin
                    col = 4'b1000;
                    if (sync_row) begin
                        next_state = state5;
                        load_num = 1'b1;
                    end
                    else begin
                        next_state = state0;
                    end
                end

            state5:
                begin
                    col = 4'b1111;
                    load_num = 0;
                    if (sync_row==0) begin
                        next_state = state0;
                    end
                    else begin
                        next_state = state1;
                    end
                end
                
            default: next_state = state0;    
        endcase
    end

endmodule

src/design/Synchro.sv
module Sincronizador (
    input logic clk_div,
    input logic rst,
    input logic [3:0] row,
    output logic [3:0] sync_row
);
    
    reg [3:0] val;

    always_ff @(posedge clk_div) begin
        if (rst) begin
            val <= 0;
            sync_row <= 0;
        end
        else begin
            val <= row;
            sync_row <= val;
        end
    end

endmodule

src/design/DivisorClock.sv
module FrecDivider (
  input logic clk,
  output logic clk_div
);

    reg [26:0] cont = 0;

    always @(posedge clk) begin
        cont <= (cont >= 269) ? 0:(cont+1);
    end

    assign clk_div = (cont == 269) ? 1'b1:1'b0;

endmodule

src/design/TopMod.sv
module MainModule(
    input logic clk,
    input logic rst, 
    input logic [3:0] row, 
    output logic [3:0] col,
    output logic [4:0] anodos,
    output logic [6:0] segmentos
);

    logic clk_div;
    logic [3:0] sync_row;
    logic [3:0] num;
    logic load_num;
    logic [7:0] num_A;
    logic [7:0] num_B;
    logic [7:0] num_o;
    logic signal_num;

    logic [15:0] num_Y;
    logic [15:0] bcd_Y;
    logic [2] q_LSB;
    /*mult_control_t mult_control;*/
    logic [15:0] num_display;

    logic load_A;
    logic load_B;
    logic load_add;
    logic shift_HQ_LQ_Q_1;
    logic add_sub;

    FrecDivider Frec(
        .clk(clk),
        .clk_div(clk_div)
    );

    Sincronizador Sync(
        .clk_div(clk_div),
        .rst(rst),
        .row(row),
        .sync_row(sync_row)
    );

    Teclado Keypad(
        .rst(rst),
        .clk_div(clk_div),
        .sync_row(sync_row),
        .col(col),
        .num(num),
        .load_num(load_num)
    );

    Numeros Multiplicandos (
        .clk(clk),
        .rst(rst),
        .num(num),
        .load_num(load_num),
        .num_o(num_o),
        .num_A(num_A),
        .num_B(num_B),
        .signal_num(signal_num)
    );
 
    control #(.n(8)) ctrl (
        .clk(clk),
        .rst(rst),
        .signal_num(signal_num),
        .q_LSB(q_LSB),
        .load_A(load_A),
        .load_B(load_B),
        .load_add(load_add),
        .shift_HQ_LQ_Q_1(shift_HQ_LQ_Q_1),
        .add_sub(add_sub)
    );

    mult_with_no_fsm #( .n(8) ) Multiplicador (
        .clk(clk),
        .rst(rst),
        .a(num_A),
        .b(num_B),
        .load_A(load_A),
        .load_B(load_B),
        .load_add(load_add),
        .shift_HQ_LQ_Q_1(shift_HQ_LQ_Q_1),
        .add_sub(add_sub),
        .q_LSB(q_LSB),
        .y(num_Y)
    );

    bin_decimal Bin_BCD(
        .binario(num_Y),
        .bcd(bcd_Y)
    );

    assign num_display = (signal_num == 0) ? num_o:bcd_Y;

    display Segmentos7(
        .clk(clk),
        .clk_div(clk_div),
        .load_num(load_num),
        .num(num_display),
        .anodos(anodos),
        .segmentos(segmentos)
    );

endmodule

src/sim/main_tb.sv
`timescale 1ns/1ps

module MainTB;

    logic clk, rst;
    logic [3:0] row, col;
    logic [4:0] anodos;
    logic [6:0] segmentos;
 
    MainModule MainTop(
        .clk(clk),
        .rst(rst),
        .row(row),
        .col(col),
        .anodos(anodos),
        .segmentos(segmentos)
        );

    always #10 clk = ~clk;

    initial begin
        clk = 0;

        row = 4'b0010;
        $display("Display=%b, Segmentos=%b, Col=%b, Row=%b", anodos, segmentos, col, row);
        #30000

        $finish;
    end

    initial begin
        $monitor("Display=%b, Segmentos=%b, Col=%b, Row=%b", anodos, segmentos, col, row);
    end

    initial begin
        $dumpfile("MainTB.vcd");
        $dumpvars(0, MainTB);
    end
    
endmodule

src/build/MainTB.vcd
$date
	Sat Nov 16 18:30:46 2024
$end
$version
	Icarus Verilog
$end
$timescale
	1ps
$end
$scope module MainTB $end
$var wire 7 ! segmentos [6:0] $end
$var wire 4 " col [3:0] $end
$var wire 5 # anodos [4:0] $end
$var reg 1 $ clk $end
$var reg 4 % row [3:0] $end
$var reg 1 & rst $end
$scope module MainTop $end
$var wire 1 $ clk $end
$var wire 4 ' row [3:0] $end
$var wire 1 & rst $end
$var wire 4 ( sync_row [3:0] $end
$var wire 1 ) signal_num $end
$var wire 1 * shift_HQ_LQ_Q_1 $end
$var wire 7 + segmentos [6:0] $end
$var wire 2 , q_LSB [0:1] $end
$var wire 8 - num_o [7:0] $end
$var wire 16 . num_display [15:0] $end
$var wire 16 / num_Y [15:0] $end
$var wire 8 0 num_B [7:0] $end
$var wire 8 1 num_A [7:0] $end
$var wire 4 2 num [3:0] $end
$var wire 1 3 load_num $end
$var wire 1 4 load_add $end
$var wire 1 5 load_B $end
$var wire 1 6 load_A $end
$var wire 4 7 col [3:0] $end
$var wire 1 8 clk_div $end
$var wire 16 9 bcd_Y [15:0] $end
$var wire 5 : anodos [4:0] $end
$var wire 1 ; add_sub $end
$scope module Bin_BCD $end
$var wire 16 < binario [15:0] $end
$var reg 16 = bcd [15:0] $end
$var integer 32 > i [31:0] $end
$upscope $end
$scope module Frec $end
$var wire 1 $ clk $end
$var wire 1 8 clk_div $end
$var reg 27 ? cont [26:0] $end
$upscope $end
$scope module Keypad $end
$var wire 1 8 clk_div $end
$var wire 1 & rst $end
$var wire 4 @ sync_row [3:0] $end
$var parameter 6 A state0 $end
$var parameter 6 B state1 $end
$var parameter 6 C state2 $end
$var parameter 6 D state3 $end
$var parameter 6 E state4 $end
$var parameter 6 F state5 $end
$var reg 4 G col [3:0] $end
$var reg 1 3 load_num $end
$var reg 6 H next_state [5:0] $end
$var reg 4 I num [3:0] $end
$var reg 6 J state [5:0] $end
$var reg 1 K sum_row $end
$upscope $end
$scope module Multiplicador $end
$var wire 1 $ clk $end
$var wire 1 & rst $end
$var wire 1 * shift_HQ_LQ_Q_1 $end
$var wire 1 4 load_add $end
$var wire 1 5 load_B $end
$var wire 1 6 load_A $end
$var wire 8 L b [7:0] $end
$var wire 1 ; add_sub $end
$var wire 8 M a [7:0] $end
$var parameter 32 N n $end
$var reg 8 O adder_sub_out [7:0] $end
$var reg 8 P hq [7:0] $end
$var reg 8 Q lq [7:0] $end
$var reg 8 R m [7:0] $end
$var reg 1 S q_1 $end
$var reg 2 T q_LSB [1:0] $end
$var reg 17 U shift [16:0] $end
$var reg 16 V y [15:0] $end
$upscope $end
$scope module Multiplicandos $end
$var wire 1 $ clk $end
$var wire 1 3 load_num $end
$var wire 4 W num [3:0] $end
$var wire 1 & rst $end
$var parameter 4 X delete $end
$var parameter 4 Y enter $end
$var parameter 3 Z s0 $end
$var parameter 3 [ s1 $end
$var parameter 3 \ s2 $end
$var parameter 3 ] s3 $end
$var parameter 3 ^ s4 $end
$var parameter 3 _ s5 $end
$var parameter 3 ` s6 $end
$var reg 3 a next_state [2:0] $end
$var reg 8 b num_A [7:0] $end
$var reg 8 c num_B [7:0] $end
$var reg 8 d num_o [7:0] $end
$var reg 8 e num_parcial [7:0] $end
$var reg 1 ) signal_num $end
$var reg 3 f state [2:0] $end
$upscope $end
$scope module Segmentos7 $end
$var wire 1 $ clk $end
$var wire 1 8 clk_div $end
$var wire 1 3 load_num $end
$var wire 16 g num [15:0] $end
$var parameter 3 h sel0 $end
$var parameter 3 i sel1 $end
$var parameter 3 j sel2 $end
$var parameter 3 k sel3 $end
$var parameter 3 l sel4 $end
$var reg 5 m anodos [4:0] $end
$var reg 4 n digito [3:0] $end
$var reg 4 o next_digito [3:0] $end
$var reg 3 p next_select [2:0] $end
$var reg 7 q segmentos [6:0] $end
$var reg 3 r select [2:0] $end
$upscope $end
$scope module Sync $end
$var wire 1 8 clk_div $end
$var wire 4 s row [3:0] $end
$var wire 1 & rst $end
$var reg 4 t sync_row [3:0] $end
$var reg 4 u val [3:0] $end
$upscope $end
$scope module ctrl $end
$var wire 1 $ clk $end
$var wire 2 v q_LSB [1:0] $end
$var wire 1 & rst $end
$var wire 1 ) signal_num $end
$var parameter 7 w idle $end
$var parameter 7 x init $end
$var parameter 32 y n $end
$var parameter 7 z res $end
$var parameter 7 { sel0 $end
$var parameter 7 | sel1 $end
$var parameter 7 } shift $end
$var parameter 7 ~ sum $end
$var reg 1 ; add_sub $end
$var reg 3 !" cont [2:0] $end
$var reg 1 6 load_A $end
$var reg 1 5 load_B $end
$var reg 1 4 load_add $end
$var reg 7 "" next_state [6:0] $end
$var reg 1 * shift_HQ_LQ_Q_1 $end
$var reg 7 #" state [6:0] $end
$var reg 2 $" z [1:0] $end
$upscope $end
$upscope $end
$upscope $end
$enddefinitions $end
$comment Show the parameter values. $end
$dumpall
b1000 ~
b100000 }
b1000000 |
b100 {
b10000 z
b1000 y
b10 x
b1 w
b100 l
b11 k
b10 j
b1 i
b0 h
b110 `
b101 _
b100 ^
b11 ]
b10 \
b1 [
b0 Z
b1011 Y
b1100 X
b1000 N
b100000 F
b10000 E
b1000 D
b100 C
b10 B
b1 A
$end
#0
$dumpvars
bx $"
bx #"
b1 ""
b111 !"
bx v
bx u
bx t
b10 s
bx r
b1111111 q
bx p
bx o
bx n
bx m
bx g
bx f
bx e
bx d
bx c
bx b
bx a
bx W
bx V
bx U
bx T
xS
bx R
bx Q
bx P
bx O
bx M
bx L
xK
bx J
bx I
bx H
bx G
bx @
b0 ?
bx >
bx =
bx <
0;
bx :
bx 9
08
bx 7
06
05
04
x3
bx 2
bx 1
bx 0
bx /
bx .
bx -
bx ,
b1111111 +
0*
x)
bx (
b10 '
x&
b10 %
0$
bx #
bx "
b1111111 !
$end
#10000
b1 ?
b1 #"
b0 r
b0 .
b0 g
b0 a
b0 0
b0 L
b0 c
b0 1
b0 M
b0 b
0)
b0 e
b0 -
b0 d
b0 p
b0 #
b0 :
b0 m
1$
#20000
0$
#30000
b10 ?
b0 o
b1 p
b1 #
b1 :
b1 m
1$
#40000
0$
#50000
b111111 !
b111111 +
b111111 q
b11 ?
b0 n
b1 r
1$
#60000
0$
#70000
b100 ?
b10 p
b10 #
b10 :
b10 m
1$
#80000
0$
#90000
b101 ?
b10 r
1$
#100000
0$
#110000
b110 ?
b11 p
b100 #
b100 :
b100 m
1$
#120000
0$
#130000
b111 ?
b11 r
1$
#140000
0$
#150000
b1000 ?
b100 p
b1000 #
b1000 :
b1000 m
1$
#160000
0$
#170000
b1001 ?
b100 r
1$
#180000
0$
#190000
b1010 ?
b0 p
b10000 #
b10000 :
b10000 m
1$
#200000
0$
#210000
b1011 ?
b0 r
1$
#220000
0$
#230000
b1100 ?
b1 p
b1 #
b1 :
b1 m
1$
#240000
0$
#250000
b1101 ?
b1 r
1$
#260000
0$
#270000
b1110 ?
b10 p
b10 #
b10 :
b10 m
1$
#280000
0$
#290000
b1111 ?
b10 r
1$
#300000
0$
#310000
b10000 ?
b11 p
b100 #
b100 :
b100 m
1$
#320000
0$
#330000
b10001 ?
b11 r
1$
#340000
0$
#350000
b10010 ?
b100 p
b1000 #
b1000 :
b1000 m
1$
#360000
0$
#370000
b10011 ?
b100 r
1$
#380000
0$
#390000
b10100 ?
b0 p
b10000 #
b10000 :
b10000 m
1$
#400000
0$
#410000
b10101 ?
b0 r
1$
#420000
0$
#430000
b10110 ?
b1 p
b1 #
b1 :
b1 m
1$
#440000
0$
#450000
b10111 ?
b1 r
1$
#460000
0$
#470000
b11000 ?
b10 p
b10 #
b10 :
b10 m
1$
#480000
0$
#490000
b11001 ?
b10 r
1$
#500000
0$
#510000
b11010 ?
b11 p
b100 #
b100 :
b100 m
1$
#520000
0$
#530000
b11011 ?
b11 r
1$
#540000
0$
#550000
b11100 ?
b100 p
b1000 #
b1000 :
b1000 m
1$
#560000
0$
#570000
b11101 ?
b100 r
1$
#580000
0$
#590000
b11110 ?
b0 p
b10000 #
b10000 :
b10000 m
1$
#600000
0$
#610000
b11111 ?
b0 r
1$
#620000
0$
#630000
b100000 ?
b1 p
b1 #
b1 :
b1 m
1$
#640000
0$
#650000
b100001 ?
b1 r
1$
#660000
0$
#670000
b100010 ?
b10 p
b10 #
b10 :
b10 m
1$
#680000
0$
#690000
b100011 ?
b10 r
1$
#700000
0$
#710000
b100100 ?
b11 p
b100 #
b100 :
b100 m
1$
#720000
0$
#730000
b100101 ?
b11 r
1$
#740000
0$
#750000
b100110 ?
b100 p
b1000 #
b1000 :
b1000 m
1$
#760000
0$
#770000
b100111 ?
b100 r
1$
#780000
0$
#790000
b101000 ?
b0 p
b10000 #
b10000 :
b10000 m
1$
#800000
0$
#810000
b101001 ?
b0 r
1$
#820000
0$
#830000
b101010 ?
b1 p
b1 #
b1 :
b1 m
1$
#840000
0$
#850000
b101011 ?
b1 r
1$
#860000
0$
#870000
b101100 ?
b10 p
b10 #
b10 :
b10 m
1$
#880000
0$
#890000
b101101 ?
b10 r
1$
#900000
0$
#910000
b101110 ?
b11 p
b100 #
b100 :
b100 m
1$
#920000
0$
#930000
b101111 ?
b11 r
1$
#940000
0$
#950000
b110000 ?
b100 p
b1000 #
b1000 :
b1000 m
1$
#960000
0$
#970000
b110001 ?
b100 r
1$
#980000
0$
#990000
b110010 ?
b0 p
b10000 #
b10000 :
b10000 m
1$
#1000000
0$
#1010000
b110011 ?
b0 r
1$
#1020000
0$
#1030000
b110100 ?
b1 p
b1 #
b1 :
b1 m
1$
#1040000
0$
#1050000
b110101 ?
b1 r
1$
#1060000
0$
#1070000
b110110 ?
b10 p
b10 #
b10 :
b10 m
1$
#1080000
0$
#1090000
b110111 ?
b10 r
1$
#1100000
0$
#1110000
b111000 ?
b11 p
b100 #
b100 :
b100 m
1$
#1120000
0$
#1130000
b111001 ?
b11 r
1$
#1140000
0$
#1150000
b111010 ?
b100 p
b1000 #
b1000 :
b1000 m
1$
#1160000
0$
#1170000
b111011 ?
b100 r
1$
#1180000
0$
#1190000
b111100 ?
b0 p
b10000 #
b10000 :
b10000 m
1$
#1200000
0$
#1210000
b111101 ?
b0 r
1$
#1220000
0$
#1230000
b111110 ?
b1 p
b1 #
b1 :
b1 m
1$
#1240000
0$
#1250000
b111111 ?
b1 r
1$
#1260000
0$
#1270000
b1000000 ?
b10 p
b10 #
b10 :
b10 m
1$
#1280000
0$
#1290000
b1000001 ?
b10 r
1$
#1300000
0$
#1310000
b1000010 ?
b11 p
b100 #
b100 :
b100 m
1$
#1320000
0$
#1330000
b1000011 ?
b11 r
1$
#1340000
0$
#1350000
b1000100 ?
b100 p
b1000 #
b1000 :
b1000 m
1$
#1360000
0$
#1370000
b1000101 ?
b100 r
1$
#1380000
0$
#1390000
b1000110 ?
b0 p
b10000 #
b10000 :
b10000 m
1$
#1400000
0$
#1410000
b1000111 ?
b0 r
1$
#1420000
0$
#1430000
b1001000 ?
b1 p
b1 #
b1 :
b1 m
1$
#1440000
0$
#1450000
b1001001 ?
b1 r
1$
#1460000
0$
#1470000
b1001010 ?
b10 p
b10 #
b10 :
b10 m
1$
#1480000
0$
#1490000
b1001011 ?
b10 r
1$
#1500000
0$
#1510000
b1001100 ?
b11 p
b100 #
b100 :
b100 m
1$
#1520000
0$
#1530000
b1001101 ?
b11 r
1$
#1540000
0$
#1550000
b1001110 ?
b100 p
b1000 #
b1000 :
b1000 m
1$
#1560000
0$
#1570000
b1001111 ?
b100 r
1$
#1580000
0$
#1590000
b1010000 ?
b0 p
b10000 #
b10000 :
b10000 m
1$
#1600000
0$
#1610000
b1010001 ?
b0 r
1$
#1620000
0$
#1630000
b1010010 ?
b1 p
b1 #
b1 :
b1 m
1$
#1640000
0$
#1650000
b1010011 ?
b1 r
1$
#1660000
0$
#1670000
b1010100 ?
b10 p
b10 #
b10 :
b10 m
1$
#1680000
0$
#1690000
b1010101 ?
b10 r
1$
#1700000
0$
#1710000
b1010110 ?
b11 p
b100 #
b100 :
b100 m
1$
#1720000
0$
#1730000
b1010111 ?
b11 r
1$
#1740000
0$
#1750000
b1011000 ?
b100 p
b1000 #
b1000 :
b1000 m
1$
#1760000
0$
#1770000
b1011001 ?
b100 r
1$
#1780000
0$
#1790000
b1011010 ?
b0 p
b10000 #
b10000 :
b10000 m
1$
#1800000
0$
#1810000
b1011011 ?
b0 r
1$
#1820000
0$
#1830000
b1011100 ?
b1 p
b1 #
b1 :
b1 m
1$
#1840000
0$
#1850000
b1011101 ?
b1 r
1$
#1860000
0$
#1870000
b1011110 ?
b10 p
b10 #
b10 :
b10 m
1$
#1880000
0$
#1890000
b1011111 ?
b10 r
1$
#1900000
0$
#1910000
b1100000 ?
b11 p
b100 #
b100 :
b100 m
1$
#1920000
0$
#1930000
b1100001 ?
b11 r
1$
#1940000
0$
#1950000
b1100010 ?
b100 p
b1000 #
b1000 :
b1000 m
1$
#1960000
0$
#1970000
b1100011 ?
b100 r
1$
#1980000
0$
#1990000
b1100100 ?
b0 p
b10000 #
b10000 :
b10000 m
1$
#2000000
0$
#2010000
b1100101 ?
b0 r
1$
#2020000
0$
#2030000
b1100110 ?
b1 p
b1 #
b1 :
b1 m
1$
#2040000
0$
#2050000
b1100111 ?
b1 r
1$
#2060000
0$
#2070000
b1101000 ?
b10 p
b10 #
b10 :
b10 m
1$
#2080000
0$
#2090000
b1101001 ?
b10 r
1$
#2100000
0$
#2110000
b1101010 ?
b11 p
b100 #
b100 :
b100 m
1$
#2120000
0$
#2130000
b1101011 ?
b11 r
1$
#2140000
0$
