src/design/7SEG.SV
module display (
    input logic clk,
    input logic clk_div,
    input logic [1:0] load_num,
    input logic [3:0] num,
    output logic [3:0] anodos,
    output logic [6:0] segmentos
);

    reg [1:0] select=0;
    reg [3:0] digito=0;

    always_ff @(posedge clk) begin
        select <= select + 1'b1;
    end

    always_ff @(posedge clk_div) begin
        if (load_num==1) begin
            digito <= num;
        end
    end

    //controla activar un display a la vez
    always_comb begin
        case (select) // traduce c/d numero BCD al 7seg correspondiente
            2'b00: begin
                anodos = 4'b0001; // Activar display 1
            end
            2'b01: begin
                anodos = 4'b0010; // Activar display 2
            end
            2'b10: begin
                anodos = 4'b0100; // Activar display 3
            end
            2'b11: begin 
                anodos = 4'b1000; // Activar display 4
            end
            default: begin
                anodos = 4'b0001;
            end
        endcase  
    end

    // controla el segmentos de acuerdo con el digito BCD
    always_comb begin
        case(digito)
            4'd0: segmentos = 7'b0111111; // 0
            4'd1: segmentos = 7'b0000110; // 1
            4'd2: segmentos = 7'b1011011; // 2
            4'd3: segmentos = 7'b1001111; // 3
            4'd4: segmentos = 7'b1100110; // 4
            4'd5: segmentos = 7'b1101101; // 5
            4'd6: segmentos = 7'b1111101; // 6
            4'd7: segmentos = 7'b0000111; // 7
            4'd8: segmentos = 7'b1111111; // 8
            4'd9: segmentos = 7'b1101111; // 9
            default: segmentos = 7'b1111111; // Desactiva los segmentos
        endcase
    end

endmodule

src/design/Teclado.sv
module Teclado (
    input logic rst,
    input logic clk_div,
    input logic [3:0] sync_row,
    output logic [3:0] col,
    output logic [3:0] num,
    output logic [1:0] load_num
);

    reg [5:0] state, next_state;
    reg sum_row;

    parameter state0 = 6'b000001, state1 = 6'b000010, state2 = 6'b000100;
    parameter state3 = 6'b001000, state4 = 6'b010000, state5 = 6'b100000;

    always @(sync_row or col) begin
        case ({sync_row, col})
            {4'b0001, 4'b0001}: num = 4'b0000; //0
            {4'b0001, 4'b0010}: num = 4'b0001; //1
            {4'b0001, 4'b0100}: num = 4'b0010; //2
            {4'b0001, 4'b1000}: num = 4'b0011; //3
            {4'b0010, 4'b0001}: num = 4'b0100; //4
            {4'b0010, 4'b0010}: num = 4'b0101; //5
            {4'b0010, 4'b0100}: num = 4'b0110; //6
            {4'b0010, 4'b1000}: num = 4'b0111; //7
            {4'b0100, 4'b0001}: num = 4'b1000; //8
            {4'b0100, 4'b0010}: num = 4'b1001; //9
            {4'b0100, 4'b0100}: num = 4'b1010; //A
            {4'b0100, 4'b1000}: num = 4'b1011; //B
            {4'b1000, 4'b0001}: num = 4'b1100; //C
            {4'b1000, 4'b0010}: num = 4'b1101; //D
            {4'b1000, 4'b0100}: num = 4'b1110; //#
            {4'b1000, 4'b1000}: num = 4'b1111; //*
            default: num = 4'b0000;
        endcase
    end

    always_ff @(posedge clk_div) begin
        if (rst) begin
            state <= state0;
        end
        else begin
            state <= next_state;
        end
    end

    always @ (state or sync_row) begin
        next_state = state;
        col = 4'b0000;
        sum_row = sync_row[3] || sync_row[2] || sync_row[1] || sync_row[0];
        case (state)
            state0:
                begin
                    col = 4'b1111;
                    load_num = 0;
                    if (sum_row) begin
                        next_state = state1;
                    end
                    else begin
                        next_state = state0;
                    end
                end
                
            state1:
                begin
                    col = 4'b0001;
                    if (sync_row) begin
                        next_state = state5;
                        load_num = 1;
                    end
                    else begin
                        next_state = state2;
                    end
                end
                
            state2:
                begin
                    col = 4'b0010;
                    if (sync_row) begin
                        next_state = state5;
                        load_num = 1;
                    end
                    else begin
                        next_state = state3;
                    end
                end
                
            state3:
                begin
                    col = 4'b0100;
                    if (sync_row) begin
                        next_state = state5;
                        load_num = 1;
                    end
                    else begin
                        next_state = state4;
                    end
                end

            state4:
                begin
                    col = 4'b1000;
                    if (sync_row) begin
                        next_state = state5;
                        load_num = 1;
                    end
                    else begin
                        next_state = state0;
                    end
                end

            state5:
                begin
                    col = 4'b1111;
                    if (sync_row==0) begin
                        next_state = state0;
                    end
                end
                
            default: next_state = state0;    
        endcase
    end

endmodule

src/design/Synchro.sv
module Sincronizador (
    input logic clk_div,
    input logic rst,
    input logic [3:0] row,
    output logic [3:0] sync_row
);
    
    reg [3:0] val;

    always_ff @(posedge clk_div) begin
        if (rst) begin
            val <= 0;
            sync_row <= 0;
        end
        else begin
            val <= row;
            sync_row <= val;
        end
    end

endmodule

src/design/DivisorClock.sv
module FrecDivider (
  input logic clk,
  output logic clk_div
);

    reg [26:0] cont = 0;

    always @(posedge clk) begin
        cont <= (cont >= 269) ? 0:(cont+1);
    end

    assign clk_div = (cont == 269) ? 1'b1:1'b0;

endmodule

src/design/TopMod.sv
module MainModule(
    input logic clk,
    input logic rst, 
    input logic [3:0] row, 
    output logic [3:0] col,
    output logic [3:0] anodos,
    output logic [6:0] segmentos
);

    logic clk_div;
    logic [3:0] sync_row;
    logic [3:0] num;
    logic [1:0] load_num;

    FrecDivider Frec(
        .clk(clk),
        .clk_div(clk_div)
    );

    Sincronizador Sync(
        .clk_div(clk_div),
        .rst(rst),
        .row(row),
        .sync_row(sync_row)
    );

    Teclado Keypad(
        .rst(rst),
        .clk_div(clk_div),
        .sync_row(sync_row),
        .col(col),
        .num(num),
        .load_num(load_num)
    );

    display Segmentos7(
        .clk(clk),
        .clk_div(clk_div),
        .load_num(load_num),
        .num(num),
        .anodos(anodos),
        .segmentos(segmentos)
    );

endmodule

src/sim/main_tb.sv
`timescale 1ns/1ps

module MainTB;

    logic clk, rst;
    logic [3:0] row, col;
    logic [3:0] anodos;
    logic [6:0] segmentos;
    
    logic clk_div;
    logic [3:0] sync_row;
    logic [3:0] num;
    logic [1:0] load_num;
 
    MainModule MainTop(
        .clk(clk),
        .rst(rst),
        .row(row),
        .col(col),
        .anodos(anodos),
        .segmentos(segmentos)
        );

    always #10 clk = ~clk;

    initial begin
        clk = 0;

        row = 4'b0010;
        $display("Display=%b, Segmentos=%b, Col=%b, Row=%b", anodos, segmentos, col, row);
        #30000

        $finish;
    end

    initial begin
        $monitor("Display=%b, Segmentos=%b, Col=%b, Row=%b", anodos, segmentos, col, row);
    end

    initial begin
        $dumpfile("MainTB.vcd");
        $dumpvars(0, MainTB);
    end
    
endmodule

src/build/MainTB.vcd
$date
	Tue Oct 29 11:06:38 2024
$end
$version
	Icarus Verilog
$end
$timescale
	1ps
$end
$scope module MainTB $end
$var wire 7 ! segmentos [6:0] $end
$var wire 4 " col [3:0] $end
$var wire 4 # anodos [3:0] $end
$var reg 1 $ clk $end
$var reg 4 % row [3:0] $end
$var reg 1 & rst $end
$scope module MainTop $end
$var wire 1 $ clk $end
$var wire 4 ' row [3:0] $end
$var wire 1 & rst $end
$var wire 4 ( sync_row [3:0] $end
$var wire 7 ) segmentos [6:0] $end
$var wire 4 * num [3:0] $end
$var wire 2 + load_num [1:0] $end
$var wire 4 , col [3:0] $end
$var wire 1 - clk_div $end
$var wire 4 . anodos [3:0] $end
$scope module Frec $end
$var wire 1 $ clk $end
$var wire 1 - clk_div $end
$var reg 27 / cont [26:0] $end
$upscope $end
$scope module Keypad $end
$var wire 1 - clk_div $end
$var wire 1 & rst $end
$var wire 4 0 sync_row [3:0] $end
$var parameter 6 1 state0 $end
$var parameter 6 2 state1 $end
$var parameter 6 3 state2 $end
$var parameter 6 4 state3 $end
$var parameter 6 5 state4 $end
$var parameter 6 6 state5 $end
$var reg 4 7 col [3:0] $end
$var reg 2 8 load_num [1:0] $end
$var reg 6 9 next_state [5:0] $end
$var reg 4 : num [3:0] $end
$var reg 6 ; state [5:0] $end
$var reg 1 < sum_row $end
$upscope $end
$scope module Segmentos7 $end
$var wire 1 $ clk $end
$var wire 1 - clk_div $end
$var wire 2 = load_num [1:0] $end
$var wire 4 > num [3:0] $end
$var reg 4 ? anodos [3:0] $end
$var reg 4 @ digito [3:0] $end
$var reg 7 A segmentos [6:0] $end
$var reg 2 B select [1:0] $end
$upscope $end
$scope module Sync $end
$var wire 1 - clk_div $end
$var wire 4 C row [3:0] $end
$var wire 1 & rst $end
$var reg 4 D sync_row [3:0] $end
$var reg 4 E val [3:0] $end
$upscope $end
$upscope $end
$upscope $end
$enddefinitions $end
$comment Show the parameter values. $end
$dumpall
b100000 6
b10000 5
b1000 4
b100 3
b10 2
b1 1
$end
#0
$dumpvars
bx E
bx D
b10 C
b0 B
b111111 A
b0 @
b1 ?
bx >
bx =
x<
bx ;
bx :
bx 9
bx 8
bx 7
bx 0
b0 /
b1 .
0-
bx ,
bx +
bx *
b111111 )
bx (
b10 '
x&
b10 %
0$
b1 #
bx "
b111111 !
$end
#10000
b10 #
b10 .
b10 ?
b1 /
b1 B
1$
#20000
0$
#30000
b100 #
b100 .
b100 ?
b10 B
b10 /
1$
#40000
0$
#50000
b1000 #
b1000 .
b1000 ?
b11 /
b11 B
1$
#60000
0$
#70000
b1 #
b1 .
b1 ?
b0 B
b100 /
1$
#80000
0$
#90000
b10 #
b10 .
b10 ?
b101 /
b1 B
1$
#100000
0$
#110000
b100 #
b100 .
b100 ?
b10 B
b110 /
1$
#120000
0$
#130000
b1000 #
b1000 .
b1000 ?
b111 /
b11 B
1$
#140000
0$
#150000
b1 #
b1 .
b1 ?
b0 B
b1000 /
1$
#160000
0$
#170000
b10 #
b10 .
b10 ?
b1001 /
b1 B
1$
#180000
0$
#190000
b100 #
b100 .
b100 ?
b10 B
b1010 /
1$
#200000
0$
#210000
b1000 #
b1000 .
b1000 ?
b1011 /
b11 B
1$
#220000
0$
#230000
b1 #
b1 .
b1 ?
b0 B
b1100 /
1$
#240000
0$
#250000
b10 #
b10 .
b10 ?
b1101 /
b1 B
1$
#260000
0$
#270000
b100 #
b100 .
b100 ?
b10 B
b1110 /
1$
#280000
0$
#290000
b1000 #
b1000 .
b1000 ?
b1111 /
b11 B
1$
#300000
0$
#310000
b1 #
b1 .
b1 ?
b0 B
b10000 /
1$
#320000
0$
#330000
b10 #
b10 .
b10 ?
b10001 /
b1 B
1$
#340000
0$
#350000
b100 #
b100 .
b100 ?
b10 B
b10010 /
1$
#360000
0$
#370000
b1000 #
b1000 .
b1000 ?
b10011 /
b11 B
1$
#380000
0$
#390000
b1 #
b1 .
b1 ?
b0 B
b10100 /
1$
#400000
0$
#410000
b10 #
b10 .
b10 ?
b10101 /
b1 B
1$
#420000
0$
#430000
b100 #
b100 .
b100 ?
b10 B
b10110 /
1$
#440000
0$
#450000
b1000 #
b1000 .
b1000 ?
b10111 /
b11 B
1$
#460000
0$
#470000
b1 #
b1 .
b1 ?
b0 B
b11000 /
1$
#480000
0$
#490000
b10 #
b10 .
b10 ?
b11001 /
b1 B
1$
#500000
0$
#510000
b100 #
b100 .
b100 ?
b10 B
b11010 /
1$
#520000
0$
#530000
b1000 #
b1000 .
b1000 ?
b11011 /
b11 B
1$
#540000
0$
#550000
b1 #
b1 .
b1 ?
b0 B
b11100 /
1$
#560000
0$
#570000
b10 #
b10 .
b10 ?
b11101 /
b1 B
1$
#580000
0$
#590000
b100 #
b100 .
b100 ?
b10 B
b11110 /
1$
#600000
0$
#610000
b1000 #
b1000 .
b1000 ?
b11111 /
b11 B
1$
#620000
0$
#630000
b1 #
b1 .
b1 ?
b0 B
b100000 /
1$
#640000
0$
#650000
b10 #
b10 .
b10 ?
b100001 /
b1 B
1$
#660000
0$
#670000
b100 #
b100 .
b100 ?
b10 B
b100010 /
1$
#680000
0$
#690000
b1000 #
b1000 .
b1000 ?
b100011 /
b11 B
1$
#700000
0$
#710000
b1 #
b1 .
b1 ?
b0 B
b100100 /
1$
#720000
0$
#730000
b10 #
b10 .
b10 ?
b100101 /
b1 B
1$
#740000
0$
#750000
b100 #
b100 .
b100 ?
b10 B
b100110 /
1$
#760000
0$
#770000
b1000 #
b1000 .
b1000 ?
b100111 /
b11 B
1$
#780000
0$
#790000
b1 #
b1 .
b1 ?
b0 B
b101000 /
1$
#800000
0$
#810000
b10 #
b10 .
b10 ?
b101001 /
b1 B
1$
#820000
0$
#830000
b100 #
b100 .
b100 ?
b10 B
b101010 /
1$
#840000
0$
#850000
b1000 #
b1000 .
b1000 ?
b101011 /
b11 B
1$
#860000
0$
#870000
b1 #
b1 .
b1 ?
b0 B
b101100 /
1$
#880000
0$
#890000
b10 #
b10 .
b10 ?
b101101 /
b1 B
1$
#900000
0$
#910000
b100 #
b100 .
b100 ?
b10 B
b101110 /
1$
#920000
0$
#930000
b1000 #
b1000 .
b1000 ?
b101111 /
b11 B
1$
#940000
0$
#950000
b1 #
b1 .
b1 ?
b0 B
b110000 /
1$
#960000
0$
#970000
b10 #
b10 .
b10 ?
b110001 /
b1 B
1$
#980000
0$
#990000
b100 #
b100 .
b100 ?
b10 B
b110010 /
1$
#1000000
0$
#1010000
b1000 #
b1000 .
b1000 ?
b110011 /
b11 B
1$
#1020000
0$
#1030000
b1 #
b1 .
b1 ?
b0 B
b110100 /
1$
#1040000
0$
#1050000
b10 #
b10 .
b10 ?
b110101 /
b1 B
1$
#1060000
0$
#1070000
b100 #
b100 .
b100 ?
b10 B
b110110 /
1$
#1080000
0$
#1090000
b1000 #
b1000 .
b1000 ?
b110111 /
b11 B
1$
#1100000
0$
#1110000
b1 #
b1 .
b1 ?
b0 B
b111000 /
1$
#1120000
0$
#1130000
b10 #
b10 .
b10 ?
b111001 /
b1 B
1$
#1140000
0$
#1150000
b100 #
b100 .
b100 ?
b10 B
b111010 /
1$
#1160000
0$
#1170000
b1000 #
b1000 .
b1000 ?
b111011 /
b11 B
1$
#1180000
0$
#1190000
b1 #
b1 .
b1 ?
b0 B
b111100 /
1$
#1200000
0$
#1210000
b10 #
b10 .
b10 ?
b111101 /
b1 B
1$
#1220000
0$
#1230000
b100 #
b100 .
b100 ?
b10 B
b111110 /
1$
#1240000
0$
#1250000
b1000 #
b1000 .
b1000 ?
b111111 /
b11 B
1$
#1260000
0$
#1270000
b1 #
b1 .
b1 ?
b0 B
b1000000 /
1$
#1280000
0$
#1290000
b10 #
b10 .
b10 ?
b1000001 /
b1 B
1$
#1300000
0$
#1310000
b100 #
b100 .
b100 ?
b10 B
b1000010 /
1$
#1320000
0$
#1330000
b1000 #
b1000 .
b1000 ?
b1000011 /
b11 B
1$
#1340000
0$
#1350000
b1 #
b1 .
b1 ?
b0 B
b1000100 /
1$
#1360000
0$
#1370000
b10 #
b10 .
b10 ?
b1000101 /
b1 B
1$
#1380000
0$
#1390000
b100 #
b100 .
b100 ?
b10 B
b1000110 /
1$
#1400000
0$
#1410000
b1000 #
b1000 .
b1000 ?
b1000111 /
b11 B
1$
#1420000
0$
#1430000
b1 #
b1 .
b1 ?
b0 B
b1001000 /
1$
#1440000
0$
#1450000
b10 #
b10 .
b10 ?
b1001001 /
b1 B
1$
#1460000
0$
#1470000
b100 #
b100 .
b100 ?
b10 B
b1001010 /
1$
#1480000
0$
#1490000
b1000 #
b1000 .
b1000 ?
b1001011 /
b11 B
1$
#1500000
0$
#1510000
b1 #
b1 .
b1 ?
b0 B
b1001100 /
1$
#1520000
0$
#1530000
b10 #
b10 .
b10 ?
b1001101 /
b1 B
1$
#1540000
0$
#1550000
b100 #
b100 .
b100 ?
b10 B
b1001110 /
1$
#1560000
0$
#1570000
b1000 #
b1000 .
b1000 ?
b1001111 /
b11 B
1$
#1580000
0$
#1590000
b1 #
b1 .
b1 ?
b0 B
b1010000 /
1$
#1600000
0$
#1610000
b10 #
b10 .
b10 ?
b1010001 /
b1 B
1$
#1620000
0$
#1630000
b100 #
b100 .
b100 ?
b10 B
b1010010 /
1$
#1640000
0$
#1650000
b1000 #
b1000 .
b1000 ?
b1010011 /
b11 B
1$
#1660000
0$
#1670000
b1 #
b1 .
b1 ?
b0 B
b1010100 /
1$
#1680000
0$
#1690000
b10 #
b10 .
b10 ?
b1010101 /
b1 B
1$
#1700000
0$
#1710000
b100 #
b100 .
b100 ?
b10 B
b1010110 /
1$
#1720000
0$
#1730000
b1000 #
b1000 .
b1000 ?
b1010111 /
b11 B
1$
#1740000
0$
#1750000
b1 #
b1 .
b1 ?
b0 B
b1011000 /
1$
#1760000
0$
#1770000
b10 #
b10 .
b10 ?
b1011001 /
b1 B
1$
#1780000
0$
#1790000
b100 #
b100 .
b100 ?
b10 B
b1011010 /
1$
#1800000
0$
#1810000
b1000 #
b1000 .
b1000 ?
b1011011 /
b11 B
1$
#1820000
0$
#1830000
b1 #
b1 .
b1 ?
b0 B
b1011100 /
1$
#1840000
0$
#1850000
b10 #
b10 .
b10 ?
b1011101 /
b1 B
1$
#1860000
0$
#1870000
b100 #
b100 .
b100 ?
b10 B
b1011110 /
1$
#1880000
0$
#1890000
b1000 #
b1000 .
b1000 ?
b1011111 /
b11 B
1$
#1900000
0$
#1910000
b1 #
b1 .
b1 ?
b0 B
b1100000 /
1$
#1920000
0$
#1930000
b10 #
b10 .
b10 ?
b1100001 /
b1 B
1$
#1940000
0$
#1950000
b100 #
b100 .
b100 ?
b10 B
b1100010 /
1$
#1960000
0$
#1970000
b1000 #
b1000 .
b1000 ?
b1100011 /
b11 B
1$
#1980000
0$
#1990000
b1 #
b1 .
b1 ?
b0 B
b1100100 /
1$
#2000000
0$
#2010000
b10 #
b10 .
b10 ?
b1100101 /
b1 B
1$
#2020000
0$
#2030000
b100 #
b100 .
b100 ?
b10 B
b1100110 /
1$
#2040000
0$
#2050000
b1000 #
b1000 .
b1000 ?
b1100111 /
b11 B
1$
#2060000
0$
#2070000
b1 #
b1 .
b1 ?
b0 B
b1101000 /
1$
#2080000
0$
#2090000
b10 #
b10 .
b10 ?
b1101001 /
b1 B
1$
#2100000
0$
#2110000
b100 #
b100 .
b100 ?
b10 B
b1101010 /
1$
#2120000
0$
#2130000
b1000 #
b1000 .
b1000 ?
b1101011 /
b11 B
1$
#2140000
0$
#2150000
b1 #
b1 .
b1 ?
b0 B
b1101100 /
1$
#2160000
0$
#2170000
b10 #
b10 .
b10 ?
b1101101 /
b1 B
1$
#2180000
0$
#2190000
b100 #
b100 .
b100 ?
b10 B
b1101110 /
1$
#2200000
0$
#2210000
b1000 #
b1000 .
b1000 ?
b1101111 /
b11 B
1$
#2220000
0$
#2230000
b1 #
b1 .
b1 ?
b0 B
b1110000 /
1$
#2240000
0$
#2250000
b10 #
b10 .
b10 ?
b1110001 /
b1 B
1$
#2260000
0$
#2270000
b100 #
b100 .
b100 ?
b10 B
b1110010 /
1$
#2280000
0$
#2290000
b1000 #
b1000 .
b1000 ?
b1110011 /
b11 B
1$
#2300000
0$
#2310000
b1 #
b1 .
b1 ?
b0 B
b1110100 /
1$
#2320000
0$
#2330000
b10 #
b10 .
b10 ?
b1110101 /
b1 B
1$
#2340000
0$
#2350000
b100 #
b100 .
b100 ?
b10 B
b1110110 /
1$
#2360000
0$
#2370000
b1000 #
b1000 .
b1000 ?
b1110111 /
b11 B
1$
#2380000
0$
#2390000
b1 #
b1 .
b1 ?
b0 B
b1111000 /
1$
#2400000
0$
#2410000
b10 #
b10 .
b10 ?
b1111001 /
b1 B
1$
#2420000
0$
#2430000
b100 #
b100 .
b100 ?
b10 B
b1111010 /
1$
#2440000
0$
#2450000
b1000 #
b1000 .
b1000 ?
b1111011 /
b11 B
1$
#2460000
0$
#2470000
b1 #
b1 .
b1 ?
b0 B
b1111100 /
1$
#2480000
0$
#2490000
b10 #
b10 .
b10 ?
b1111101 /
b1 B
1$
#2500000
0$
#2510000
b100 #
b100 .
b100 ?
b10 B
b1111110 /
1$
#2520000
0$
#2530000
b1000 #
b1000 .
b1000 ?
b1111111 /
b11 B
1$
#2540000
0$
#2550000
b1 #
b1 .
b1 ?
b0 B
b10000000 /
1$
#2560000
0$
#2570000
b10 #
b10 .
b10 ?
b10000001 /
b1 B
1$
#2580000
0$
#2590000
b100 #
b100 .
b100 ?
b10 B
b10000010 /
1$
#2600000
0$
#2610000
b1000 #
b1000 .
b1000 ?
b10000011 /
b11 B
1$
#2620000
0$
#2630000
b1 #
b1 .
b1 ?
b0 B
b10000100 /
1$
#2640000
0$
#2650000
b10 #
b10 .
b10 ?
b10000101 /
b1 B
1$
#2660000
0$
#2670000
b100 #
b100 .
b100 ?
b10 B
b10000110 /
1$
#2680000
0$
#2690000
b1000 #
b1000 .
b1000 ?
b10000111 /
b11 B
1$
#2700000
0$
#2710000
b1 #
b1 .
b1 ?
b0 B
b10001000 /
1$
#2720000
0$
#2730000
b10 #
b10 .
b10 ?
b10001001 /
b1 B
1$
#2740000
0$
#2750000
b100 #
b100 .
b100 ?
b10 B
b10001010 /
1$
#2760000
0$
#2770000
b1000 #
b1000 .
b1000 ?
b10001011 /
b11 B
1$
#2780000
0$
#2790000
b1 #
b1 .
b1 ?
b0 B
b10001100 /
1$
#2800000
0$
#2810000
b10 #
b10 .
b10 ?
b10001101 /
b1 B
1$
#2820000
0$
#2830000
b100 #
b100 .
b100 ?
b10 B
b10001110 /
1$
#2840000
0$
#2850000
b1000 #
b1000 .
b1000 ?
b10001111 /
b11 B
1$
#2860000
0$
#2870000
b1 #
b1 .
b1 ?
b0 B
b10010000 /
1$
#2880000
0$
#2890000
b10 #
b10 .
b10 ?
b10010001 /
b1 B
1$
#2900000
0$
#2910000
b100 #
b100 .
b100 ?
b10 B
b10010010 /
1$
#2920000
0$
#2930000
b1000 #
b1000 .
b1000 ?
b10010011 /
b11 B
1$
#2940000
0$
#2950000
b1 #
b1 .
b1 ?
b0 B
b10010100 /
1$
#2960000
0$
#2970000
b10 #
b10 .
b10 ?
b10010101 /
b1 B
1$
#2980000
0$
#2990000
b100 #
b100 .
b100 ?
b10 B
b10010110 /
1$
#3000000
0$
#3010000
b1000 #
b1000 .
b1000 ?
b10010111 /
b11 B
1$
#3020000
0$
#3030000
b1 #
b1 .
b1 ?
b0 B
b10011000 /
1$
#3040000
0$
#3050000
b10 #
b10 .
b10 ?
b10011001 /
b1 B
1$
#3060000
0$
#3070000
b100 #
b100 .
b100 ?
b10 B
b10011010 /
1$
#3080000
0$
#3090000
b1000 #
b1000 .
b1000 ?
b10011011 /
b11 B
1$
#3100000
0$
#3110000
b1 #
b1 .
b1 ?
b0 B
b10011100 /
1$
#3120000
0$
#3130000
b10 #
b10 .
b10 ?
b10011101 /
b1 B
1$
#3140000
0$
#3150000
b100 #
b100 .
b100 ?
b10 B
b10011110 /
1$
#3160000
0$
#3170000
b1000 #
b1000 .
b1000 ?
b10011111 /
b11 B
1$
#3180000
0$
#3190000
b1 #
b1 .
b1 ?
b0 B
b10100000 /
1$
#3200000
0$
#3210000
b10 #
b10 .
b10 ?
b10100001 /
b1 B
1$
#3220000
0$
#3230000
b100 #
b100 .
b100 ?
b10 B
b10100010 /
1$
#3240000
0$
#3250000
b1000 #
b1000 .
b1000 ?
b10100011 /
b11 B
1$
#3260000
0$
#3270000
b1 #
b1 .
b1 ?
b0 B
b10100100 /
1$
#3280000
0$
#3290000
b10 #
b10 .
b10 ?
b10100101 /
b1 B
1$
#3300000
0$
#3310000
b100 #
b100 .
b100 ?
b10 B
b10100110 /
1$
#3320000
0$
#3330000
b1000 #
b1000 .
b1000 ?
b10100111 /
b11 B
1$
#3340000
0$
#3350000
b1 #
b1 .
b1 ?
b0 B
b10101000 /
1$
#3360000
0$
#3370000
b10 #
b10 .
b10 ?
b10101001 /
b1 B
1$
#3380000
0$
#3390000
b100 #
b100 .
b100 ?
b10 B
b10101010 /
1$
#3400000
0$
#3410000
b1000 #
b1000 .
b1000 ?
b10101011 /
b11 B
1$
#3420000
0$
#3430000
b1 #
b1 .
b1 ?
b0 B
b10101100 /
1$
#3440000
0$
#3450000
b10 #
b10 .
b10 ?
b10101101 /
b1 B
1$
#3460000
0$
#3470000
b100 #
b100 .
b100 ?
b10 B
b10101110 /
1$
#3480000
0$
#3490000
b1000 #
b1000 .
b1000 ?
b10101111 /
b11 B
1$
#3500000
0$
#3510000
b1 #
b1 .
b1 ?
b0 B
b10110000 /
1$
#3520000
0$
#3530000
b10 #
b10 .
b10 ?
b10110001 /
b1 B
1$
#3540000
0$
#3550000
b100 #
b100 .
b100 ?
b10 B
b10110010 /
1$
#3560000
0$
#3570000
b1000 #
b1000 .
b1000 ?
b10110011 /
b11 B
1$
#3580000
0$
#3590000
b1 #
b1 .
b1 ?
b0 B
b10110100 /
1$
#3600000
0$
#3610000
b10 #
b10 .
b10 ?
b10110101 /
b1 B
1$
#3620000
0$
#3630000
b100 #
b100 .
b100 ?
b10 B
b10110110 /
1$
#3640000
0$
#3650000
b1000 #
b1000 .
b1000 ?
b10110111 /
b11 B
1$
#3660000
0$
#3670000
b1 #
b1 .
b1 ?
b0 B
b10111000 /
1$
#3680000
0$
#3690000
b10 #
b10 .
b10 ?
b10111001 /
b1 B
1$
#3700000
0$
#3710000
b100 #
b100 .
b100 ?
b10 B
b10111010 /
1$
#3720000
0$
#3730000
b1000 #
b1000 .
b1000 ?
b10111011 /
b11 B
1$
#3740000
0$
#3750000
b1 #
b1 .
b1 ?
b0 B
b10111100 /
1$
#3760000
0$
#3770000
b10 #
b10 .
b10 ?
b10111101 /
b1 B
1$
#3780000
0$
#3790000
b100 #
b100 .
b100 ?
b10 B
b10111110 /
1$
#3800000
0$
#3810000
b1000 #
b1000 .
b1000 ?
b10111111 /
b11 B
1$
#3820000
0$
#3830000
b1 #
b1 .
b1 ?
b0 B
b11000000 /
1$
#3840000
0$
#3850000
b10 #
b10 .
b10 ?
b11000001 /
b1 B
1$
#3860000
0$
#3870000
b100 #
b100 .
b100 ?
b10 B
b11000010 /
1$
#3880000
0$
#3890000
b1000 #
b1000 .
b1000 ?
b11000011 /
b11 B
1$
#3900000
0$
#3910000
b1 #
b1 .
b1 ?
b0 B
b11000100 /
1$
#3920000
0$
#3930000
b10 #
b10 .
b10 ?
b11000101 /
b1 B
1$
#3940000
0$
#3950000
b100 #
b100 .
b100 ?
b10 B
b11000110 /
1$
#3960000
0$
#3970000
b1000 #
b1000 .
b1000 ?
b11000111 /
b11 B
1$
#3980000
0$
#3990000
b1 #
b1 .
b1 ?
b0 B
b11001000 /
1$
#4000000
0$
#4010000
b10 #
b10 .
b10 ?
b11001001 /
b1 B
1$
#4020000
0$
#4030000
b100 #
b100 .
b100 ?
b10 B
b11001010 /
1$
#4040000
0$
#4050000
b1000 #
b1000 .
b1000 ?
b11001011 /
b11 B
1$
#4060000
0$
#4070000
b1 #
b1 .
b1 ?
b0 B
b11001100 /
1$
#4080000
0$
#4090000
b10 #
b10 .
b10 ?
b11001101 /
b1 B
1$
#4100000
0$
#4110000
b100 #
b100 .
b100 ?
b10 B
b11001110 /
1$
#4120000
0$
#4130000
b1000 #
b1000 .
b1000 ?
b11001111 /
b11 B
1$
#4140000
0$
#4150000
b1 #
b1 .
b1 ?
b0 B
b11010000 /
1$
#4160000
0$
#4170000
b10 #
b10 .
b10 ?
b11010001 /
b1 B
1$
#4180000
0$
#4190000
b100 #
b100 .
b100 ?
b10 B
b11010010 /
1$
#4200000
0$
#4210000
b1000 #
b1000 .
b1000 ?
b11010011 /
b11 B
1$
#4220000
0$
#4230000
b1 #
b1 .
b1 ?
b0 B
b11010100 /
1$
#4240000
0$
#4250000
b10 #
b10 .
b10 ?
b11010101 /
b1 B
1$
#4260000
0$
#4270000
b100 #
b100 .
b100 ?
b10 B
b11010110 /
1$
#4280000
0$
#4290000
b1000 #
b1000 .
b1000 ?
b11010111 /
b11 B
1$
#4300000
0$
#4310000
b1 #
b1 .
b1 ?
b0 B
b11011000 /
1$
#4320000
0$
#4330000
b10 #
b10 .
b10 ?
b11011001 /
b1 B
1$
#4340000
0$
#4350000
b100 #
b100 .
b100 ?
b10 B
b11011010 /
1$
#4360000
0$
#4370000
b1000 #
b1000 .
b1000 ?
b11011011 /
b11 B
1$
#4380000
0$
#4390000
b1 #
b1 .
b1 ?
b0 B
b11011100 /
1$
#4400000
0$
#4410000
b10 #
b10 .
b10 ?
b11011101 /
b1 B
1$
#4420000
0$
#4430000
b100 #
b100 .
b100 ?
b10 B
b11011110 /
1$
#4440000
0$
#4450000
b1000 #
b1000 .
b1000 ?
b11011111 /
b11 B
1$
#4460000
0$
#4470000
b1 #
b1 .
b1 ?
b0 B
b11100000 /
1$
#4480000
0$
#4490000
b10 #
b10 .
b10 ?
b11100001 /
b1 B
1$
#4500000
0$
#4510000
b100 #
b100 .
b100 ?
b10 B
b11100010 /
1$
#4520000
0$
#4530000
b1000 #
b1000 .
b1000 ?
b11100011 /
b11 B
1$
#4540000
0$
#4550000
b1 #
b1 .
b1 ?
b0 B
b11100100 /
1$
#4560000
0$
#4570000
b10 #
b10 .
b10 ?
b11100101 /
b1 B
1$
#4580000
0$
#4590000
b100 #
b100 .
b100 ?
b10 B
b11100110 /
1$
#4600000
0$
#4610000
b1000 #
b1000 .
b1000 ?
b11100111 /
b11 B
1$
#4620000
0$
#4630000
b1 #
b1 .
b1 ?
b0 B
b11101000 /
1$
#4640000
0$
#4650000
b10 #
b10 .
b10 ?
b11101001 /
b1 B
1$
#4660000
0$
#4670000
b100 #
b100 .
b100 ?
b10 B
b11101010 /
1$
#4680000
0$
#4690000
b1000 #
b1000 .
b1000 ?
b11101011 /
b11 B
1$
#4700000
0$
#4710000
b1 #
b1 .
b1 ?
b0 B
b11101100 /
1$
#4720000
0$
#4730000
b10 #
b10 .
b10 ?
b11101101 /
b1 B
1$
#4740000
0$
#4750000
b100 #
b100 .
b100 ?
b10 B
b11101110 /
1$
#4760000
0$
#4770000
b1000 #
b1000 .
b1000 ?
b11101111 /
b11 B
1$
#4780000
0$
#4790000
b1 #
b1 .
b1 ?
b0 B
b11110000 /
1$
#4800000
0$
#4810000
b10 #
b10 .
b10 ?
b11110001 /
b1 B
1$
#4820000
0$
#4830000
b100 #
b100 .
b100 ?
b10 B
b11110010 /
1$
#4840000
0$
