src/design/7SEG.SV
module display (
    input logic clk,
    input logic load_num,
    input logic [15:0] num,
    output logic [4:0] anodos,
    output logic [6:0] segmentos
);

    reg [2:0] select, next_select;
    reg [3:0] digito, next_digito;

    parameter sel0 = 3'b000, sel1 = 3'b001, sel2 = 3'b010, sel3 = 3'b011, sel4 = 3'b100;

    always_ff @(posedge clk) begin
        select <= next_select;
        digito <= next_digito;
    end

    //controla activar un display a la vez
    always_comb begin
        case (select) // traduce c/d numero BCD al 7seg correspondiente
            sel0: begin
                anodos = 5'b00001; // Activar display 1
                next_select = sel1;
                next_digito = num[3:0];
            end

            sel1: begin
                anodos = 5'b00010; // Activar display 2
                next_select = sel2;
                next_digito = num[7:4];
            end

            sel2: begin
                anodos = 5'b00100; // Activar display 3
                next_select = sel3;
                next_digito = num[11:8];
            end

            sel3: begin 
                anodos = 5'b01000; // Activar display 4
                next_select = sel4;
                next_digito = num[15:12];
            end
            
            sel4: begin
                anodos = 5'b10000;
                next_select = sel0;
                next_digito = 4'b0000;
            end

            default: begin
                anodos = 5'b00000;
                next_select = sel0;
                next_digito = num[3:0];
            end
        endcase  
    end

    // controla el segmentos de acuerdo con el digito BCD
    always_comb begin
        case(digito)
            4'd0: segmentos = 7'b0111111; // 0
            4'd1: segmentos = 7'b0000110; // 1
            4'd2: segmentos = 7'b1011011; // 2
            4'd3: segmentos = 7'b1001111; // 3
            4'd4: segmentos = 7'b1100110; // 4
            4'd5: segmentos = 7'b1101101; // 5
            4'd6: segmentos = 7'b1111101; // 6
            4'd7: segmentos = 7'b0000111; // 7
            4'd8: segmentos = 7'b1111111; // 8
            4'd9: segmentos = 7'b1101111; // 9
            default: segmentos = 7'b1111111; // Desactiva los segmentos
        endcase
    end

endmodule

src/design/Conv-BCD.sv
module bin_decimal ( //usando el algoritmo de doble dabble
    input [15:0] binario, //13 bits para manejar el acarreo
    output reg [15:0] bcd// salida BCD 4 digitos
);

    integer i;
    always @ (binario) begin
        bcd = 16'b0;  // Inicializar BCD a 0
        for (i = 0; i < 15; i = i + 1) begin
            // Si cualquier grupo de 4 bits en BCD es mayor o igual a 5, suma 3
            if (bcd[3:0] >= 5) bcd[3:0] = bcd[3:0] + 3;
            if (bcd[7:4] >= 5) bcd[7:4] = bcd[7:4] + 3;
            if (bcd[11:8] >= 5) bcd[11:8] = bcd[11:8] + 3;
            if (bcd[15:12] >= 5) bcd[15:12] = bcd[15:12] + 3;

            bcd = {bcd[14:0], binario[15-i]}; // desplaza los bits del binario
        end
    end

endmodule

src/design/mult_datapath.sv
module mult_with_no_fsm #(
    parameter N = 8
    ) (
    input logic clk ,
    input logic rst ,
    input logic [N-1:0] A,
    input logic [N-1:0] B,
    input logic load_A,
    input logic load_B,
    input logic load_add,
    input logic shift_HQ_LQ_Q_1,
    input logic add_sub,
    output logic [1:0] Q_LSB,
    output logic [2*N-1:0] Y
) ;


logic [N-1:0] M;
logic [N-1:0] adder_sub_out ;
logic [2*N: 0 ] shift ;
logic [N-1:0] HQ;
logic [N-1:0] LQ;
logic Q_1;

//reg_M
always_ff@ (posedge clk , posedge rst ) begin
    if ( rst )
        M <='b0 ;
    else
        M <= (load_A) ? A : M;
    end

// adder / sub
always_comb begin
    if (add_sub )
        adder_sub_out = M + HQ;
    else
        adder_sub_out = M - HQ;
    end
// shift registers
always_comb begin
    Y = {HQ,LQ} ;
    HQ = shift[2*N:N+1];
    LQ = shift[N:1] ;
    Q_1 = shift[0] ;
    Q_LSB = {LQ[0] ,Q_1} ;
end


always_ff@ (posedge clk , posedge rst ) begin
    if ( rst )
        shift <= 'b0 ;
    else if (shift_HQ_LQ_Q_1)
        // arithmetic shift
        shift <= $signed (shift)>>>1;
         else begin
            if ( load_B )
                shift [N:1] <= B;
            if ( load_add )
                shift [2*N:N+1] <= adder_sub_out ;
        end
    end


endmodule

src/design/mult_control.sv
module control #(
    parameter n = 8
    ) (
    input logic clk,
    input logic rst,
    input logic signal_num,
    input logic [1:0] q_LSB,
    output logic load_A,
    output logic load_B,
    output logic load_add,
    output logic shift_HQ_LQ_Q_1,
    output logic add_sub
    );

    reg [6:0] state, next_state;
    reg [2:0] cont;
    reg [1:0] z;

    parameter idle = 7'b0000001, init = 7'b0000010, sel0 = 7'b0000100; 
    parameter sum = 7'b0001000, res = 7'b0010000, shift = 7'b0100000, sel1 = 7'b1000000;

    always_ff @(posedge clk) begin
        if (rst) begin
            cont <= 3'b111;
            state <= idle;
        end
        else begin
            state <= next_state;
        end
    end

    always_comb begin
        next_state = state;        
        cont = 3'b111; 
        load_A = 1'b0;
        load_B = 1'b0;
        load_add = 1'b0;
        shift_HQ_LQ_Q_1 = 1'b0;
        add_sub = 1'b0;
        z = 1'b0;
        case (state)
            idle: begin
                if (signal_num) begin
                    next_state = init;
                end
                else begin
                    next_state = idle;
                end
            end

            init: begin
                cont = 3'b111;
                load_A = 1'b1;
                load_B = 1'b1;
                load_add = 1'b0;
                shift_HQ_LQ_Q_1 = 1'b0;
                add_sub = 1'b0;
                next_state = sel0;
            end

            sel0: begin
                cont = 3'b111;
                load_A = 1'b0;
                load_B = 1'b0;
                load_add = 1'b0;
                shift_HQ_LQ_Q_1 = 1'b1;
                add_sub = 1'b0;
                if (q_LSB[0] == q_LSB[1]) begin
                    next_state = shift;
                end
                else if (q_LSB[0]) begin
                    next_state = sum;
                end
                else if (q_LSB[1]) begin
                    next_state = res;
                end
            end

            sum: begin
                cont = 3'b111;
                load_A = 1'b0;
                load_B = 1'b0;
                load_add = 1'b1;
                shift_HQ_LQ_Q_1 = 1'b0;
                add_sub = 1'b1;
                next_state = shift;
            end

            res: begin
                cont = 3'b111;
                load_A = 1'b0;
                load_B = 1'b0;
                load_add = 1'b1;
                shift_HQ_LQ_Q_1 = 1'b0;
                add_sub = 1'b0;
                next_state = shift;
            end

            shift: begin
                cont = cont - 1'b1;
                if (cont == 3'b000) begin
                    z = 1'b1;
                end
                else begin
                    z = 1'b0;
                end
                next_state = sel1;
            end

            sel1: begin
                if (z) begin
                    next_state = idle;
                end
                else begin
                    next_state = sel0;
                end
            end

            default: begin
                cont = 3'b111;
                load_A = 1'b0;
                load_B = 1'b0;
                load_add = 1'b0;
                shift_HQ_LQ_Q_1 = 1'b0;
                add_sub = 1'b0;
                next_state = idle;
                z = 1'b0;
            end
        endcase
    end

endmodule

src/design/Numero.sv
module Numeros (
    input logic clk,
    input logic rst,
    input logic [3:0] num,
    input logic load_num,
    output logic [7:0] num_o,
    output logic [7:0] num_A, 
    output logic [7:0] num_B,
    output logic signal_num
);

    reg [2:0] state, next_state;
    logic [7:0] num_parcial;

    parameter s0 = 3'b000, s1 = 3'b001, s2 = 3'b010, s3 = 3'b011; 
    parameter s4 = 3'b100, s5 = 3'b101, s6 = 3'b110;
    parameter enter = 4'b1011, delete = 4'b1100;
    
    always_ff @(posedge clk) begin
        if (rst) begin
            state <= s0;
        end
        else if (load_num) begin
            state <= next_state;
        end
    end

    always @ (state) begin
        num_o = 8'b0;
        signal_num = 1'b0;
        num_parcial = 8'b0;
        num_A = 8'b0;
        num_B = 8'b0;
        next_state = s0;
        case (state)
            s0: begin
                num_parcial = 8'b0;
                num_A = 8'b0;
                num_B = 8'b0;
                signal_num = 1'b0;
                if (load_num) begin
                    if (num == enter) begin
                        next_state = s3;
                    end
                    else if (num == delete) begin
                        next_state = s0;
                    end
                    else begin
                        num_o = num;
                        num_parcial = num;
                        next_state = s1;
                    end
                end
            end

            s1: begin
                if (load_num) begin
                    if (num == enter) begin
                        num_A = num_parcial;
                        next_state = s3;
                    end
                    else if (num == delete) begin
                        num_parcial = 8'b0;
                        next_state = s0;
                    end
                    else begin
                        num_o = {num_parcial[7:4], num};
                        num_parcial = num_parcial*8'd10 + num;
                        next_state = s2;
                    end
                end
            end

            s2: begin
                if (load_num) begin
                    if (num == enter) begin
                        num_A = num_parcial;
                        next_state = s3;
                    end
                    else if (num == delete) begin
                        num_o = {4'b0000, num_o[7:4]};
                        num_parcial = num_o;
                        next_state = s1;
                    end
                end
            end

            s3: begin
                if (load_num) begin
                    if (num == enter) begin
                        signal_num = 1'b1;
                        next_state = s6;
                    end
                    else if (num == delete) begin
                        next_state = s3;
                    end
                    else begin
                        num_o = num;
                        num_parcial = num;
                        next_state = s4;
                    end
                end
            end

            s4: begin
                if (load_num) begin
                    if (num == enter) begin
                        num_B = num_parcial;
                        signal_num = 1'b1;
                        next_state = s6;
                    end
                    else if (num == delete) begin
                        num_o = 8'b0;
                        num_parcial = 8'b0;
                        next_state = s3;
                    end
                    else begin
                        num_o = {num_parcial[7:4], num};
                        num_parcial = num_parcial*4'b1010 + num;
                        next_state = s5;
                    end
                end
            end

            s5: begin
                if (load_num) begin
                    if (num == enter) begin
                        num_B = num_parcial;
                        signal_num = 1'b1;
                        next_state = s6;
                    end
                    else if (num == delete) begin
                        num_o = {4'b0000, num_o};
                        num_parcial = num_o;
                        next_state = s4;
                    end
                end
            end

            s6: begin
                if (load_num) begin
                    if (num == enter) begin
                        signal_num = 1'b0;
                        next_state = s0;
                    end
                end
            end

            default: begin
                num_o = 8'b0;
                signal_num = 1'b0;
                num_parcial = 8'b0;
                num_A = 8'b0;
                num_B = 8'b0;
                next_state = s0;
            end

        endcase
    end

endmodule

src/design/Teclado.sv
module Teclado (
    input logic rst,
    input logic clk_div,
    input logic [3:0] sync_row,
    output logic [3:0] col,
    output logic [3:0] num,
    output logic load_num
);

    reg [5:0] state, next_state;
    logic sum_row;

    parameter state0 = 6'b000001, state1 = 6'b000010, state2 = 6'b000100;
    parameter state3 = 6'b001000, state4 = 6'b010000, state5 = 6'b100000;

    always @ (sync_row or col) begin
        case ({sync_row, col})
            {4'b0001, 4'b0001}: num = 4'b0000; //0
            {4'b0001, 4'b0010}: num = 4'b0001; //1
            {4'b0001, 4'b0100}: num = 4'b0010; //2
            {4'b0001, 4'b1000}: num = 4'b0011; //3
            {4'b0010, 4'b0001}: num = 4'b0100; //4
            {4'b0010, 4'b0010}: num = 4'b0101; //5
            {4'b0010, 4'b0100}: num = 4'b0110; //6
            {4'b0010, 4'b1000}: num = 4'b0111; //7
            {4'b0100, 4'b0001}: num = 4'b1000; //8
            {4'b0100, 4'b0010}: num = 4'b1001; //9
            {4'b0100, 4'b0100}: num = 4'b1010; //A - Signo Negativo
            {4'b0100, 4'b1000}: num = 4'b1011; //B - Intro
            {4'b1000, 4'b0001}: num = 4'b1100; //C - Borrar
            //{4'b1000, 4'b0010}: num = 4'b1101; //D
            //{4'b1000, 4'b0100}: num = 4'b1110; //#
            //{4'b1000, 4'b1000}: num = 4'b1111; //*
            default: num = 4'b0000;
        endcase
    end

    always_ff @(posedge clk_div) begin
        if (rst) begin
            state <= state0;
        end
        else begin
            state <= next_state;
        end
    end

    always @ (clk_div) begin
        next_state = state0;
        col = 4'b1111;
        sum_row = |sync_row;
        load_num = 1'b0;
        case (state)
            state0:
                begin
                    col = 4'b1111;
                    load_num = 1'b0;
                    if (sum_row) begin
                        next_state = state1;
                    end
                    else begin
                        next_state = state0;
                    end
                end
                
            state1:
                begin
                    col = 4'b0001;
                    if (sync_row != 4'b0000) begin
                        load_num = 1'b1;
                        next_state = state5;
                    end
                    else begin
                        next_state = state2;
                    end
                end
                
            state2:
                begin
                    col = 4'b0010;
                    if (sync_row != 4'b0000) begin
                        load_num = 1'b1;
                        next_state = state5;
                    end
                    else begin
                        next_state = state3;
                    end
                end
                
            state3:
                begin
                    col = 4'b0100;
                    if (sync_row != 4'b0000) begin
                        load_num = 1'b1;
                        next_state = state5;
                    end
                    else begin
                        next_state = state4;
                    end
                end

            state4:
                begin
                    col = 4'b1000;
                    if (sync_row != 4'b0000) begin
                        load_num = 1'b1;
                        next_state = state5;
                    end
                    else begin
                        next_state = state0;
                    end
                end

            state5:
                begin
                    col = 4'b1111;
                    if (sync_row==4'b0000) begin
                        next_state = state0;
                    end
                    else begin
                        next_state = state1;
                    end
                end
                
            default: next_state = state0;    
        endcase
    end

endmodule

src/design/Synchro.sv
module Sincronizador (
    input logic clk_div,
    input logic rst,
    input logic [3:0] row,
    output logic [3:0] sync_row
);
    
    reg [3:0] val;

    always_ff @(posedge clk_div) begin
        if (rst) begin
            val <= 0;
            sync_row <= 0;
        end
        else begin
            val <= row;
            sync_row <= val;
        end
    end

endmodule

src/design/DivisorClock.sv
module FrecDivider (
  input logic clk,
  output logic clk_div
);

  reg [27:0] cont = 28'd0;
  parameter div = 28'd27000;
  
  always @(posedge clk) begin
    if (cont >= (div-28'd1)) begin cont <= 0; end
    else begin cont <= cont+28'd1; end
  end

  assign clk_div = (cont<div/2) ? 1'b1:1'b0;

endmodule

src/design/TopMod.sv
module MainModule(
    input logic clk,
    input logic rst, 
    input logic [3:0] row, 
    output logic [3:0] col,
    output logic [4:0] anodos,
    output logic [6:0] segmentos
);

    logic clk_div;
    logic [3:0] sync_row;
    logic [3:0] num;
    logic load_num;
    logic [7:0] num_A;
    logic [7:0] num_B;
    logic [7:0] num_o;
    logic signal_num;

    logic [15:0] num_Y;
    logic [15:0] bcd_Y;
    logic [1:0] q_LSB;
    /*mult_control_t mult_control;*/
    logic [15:0] num_display;

    logic load_A;
    logic load_B;
    logic load_add;
    logic shift_HQ_LQ_Q_1;
    logic add_sub;

    FrecDivider Frec(
        .clk(clk),
        .clk_div(clk_div)
    );

    Sincronizador Sync(
        .clk_div(clk_div),
        .rst(rst),
        .row(row),
        .sync_row(sync_row)
    );

    Teclado Keypad(
        .rst(rst),
        .clk_div(clk),
        .sync_row(row),
        .col(col),
        .num(num),
        .load_num(load_num)
    );

    Numeros Multiplicandos (
        .clk(clk),
        .rst(rst),
        .num(num),
        .load_num(load_num),
        .num_o(num_o),
        .num_A(num_A),
        .num_B(num_B),
        .signal_num(signal_num)
    );
 
    control #(.n(8)) ctrl (
        .clk(clk_div),
        .rst(rst),
        .signal_num(signal_num),
        .q_LSB(q_LSB),
        .load_A(load_A),
        .load_B(load_B),
        .load_add(load_add),
        .shift_HQ_LQ_Q_1(shift_HQ_LQ_Q_1),
        .add_sub(add_sub)
    );

    mult_with_no_fsm #( .N(8) ) Multiplicador (
        .clk(clk_div),
        .rst(rst),
        .A(num_A),
        .B(num_B),
        .load_A(load_A),
        .load_B(load_B),
        .load_add(load_add),
        .shift_HQ_LQ_Q_1(shift_HQ_LQ_Q_1),
        .add_sub(add_sub),
        .Q_LSB(q_LSB),
        .Y(num_Y)
    );

    bin_decimal Bin_BCD(
        .binario(num_Y),
        .bcd(bcd_Y)
    );

    always_comb begin
        num_display = (signal_num == 0) ? num_o:bcd_Y;
    end

    display Segmentos7(
        .clk(clk),
        .load_num(load_num),
        .num(num_display),
        .anodos(anodos),
        .segmentos(segmentos)
    );

endmodule

src/sim/main_tb.sv
`timescale 1ns/1ps

module MainTB;

    logic clk, rst;
    logic [3:0] row, col;
    logic [4:0] anodos;
    logic [6:0] segmentos;
 
    MainModule MainTop(
        .clk(clk),
        .rst(rst),
        .row(row),
        .col(col),
        .anodos(anodos),
        .segmentos(segmentos)
        );

    always #1 clk = ~clk;

    initial begin
        clk = 0;
        row = 4'b0000;
        #100
        row = 4'b0010;
        #270
        row = 4'b0000;
        #100
        row = 4'b0100;
        #270
        row = 4'b0000;
        #100
        row = 4'b0100;
        #270
        row = 4'b0000;
        
        #100
        row = 4'b0100;
        #270
        row = 4'b0000;
        #100
        row = 4'b1000;
        #270
        row = 4'b0000;
        #100
        row = 4'b0001;
        #270
        row = 4'b0000;
        
        #300
        $finish;
    end

    initial begin
        $monitor("Display=%b, Segmentos=%b, Col=%b, Row=%b", anodos, segmentos, col, row);
    end

    initial begin
        $dumpfile("MainTB.vcd");
        $dumpvars(0, MainTB);
    end
    
endmodule

src/build/MainTB.vcd
$date
	Wed Nov 20 09:56:31 2024
$end
$version
	Icarus Verilog
$end
$timescale
	1ps
$end
$scope module MainTB $end
$var wire 7 ! segmentos [6:0] $end
$var wire 4 " col [3:0] $end
$var wire 5 # anodos [4:0] $end
$var reg 1 $ clk $end
$var reg 4 % row [3:0] $end
$var reg 1 & rst $end
$scope module MainTop $end
$var wire 1 $ clk $end
$var wire 4 ' row [3:0] $end
$var wire 1 & rst $end
$var wire 4 ( sync_row [3:0] $end
$var wire 1 ) signal_num $end
$var wire 1 * shift_HQ_LQ_Q_1 $end
$var wire 7 + segmentos [6:0] $end
$var wire 2 , q_LSB [1:0] $end
$var wire 8 - num_o [7:0] $end
$var wire 16 . num_Y [15:0] $end
$var wire 8 / num_B [7:0] $end
$var wire 8 0 num_A [7:0] $end
$var wire 4 1 num [3:0] $end
$var wire 1 2 load_num $end
$var wire 1 3 load_add $end
$var wire 1 4 load_B $end
$var wire 1 5 load_A $end
$var wire 4 6 col [3:0] $end
$var wire 1 7 clk_div $end
$var wire 16 8 bcd_Y [15:0] $end
$var wire 5 9 anodos [4:0] $end
$var wire 1 : add_sub $end
$var reg 16 ; num_display [15:0] $end
$scope module Bin_BCD $end
$var wire 16 < binario [15:0] $end
$var reg 16 = bcd [15:0] $end
$var integer 32 > i [31:0] $end
$upscope $end
$scope module Frec $end
$var wire 1 $ clk $end
$var wire 1 7 clk_div $end
$var parameter 28 ? div $end
$var reg 28 @ cont [27:0] $end
$upscope $end
$scope module Keypad $end
$var wire 1 $ clk_div $end
$var wire 1 & rst $end
$var wire 4 A sync_row [3:0] $end
$var parameter 6 B state0 $end
$var parameter 6 C state1 $end
$var parameter 6 D state2 $end
$var parameter 6 E state3 $end
$var parameter 6 F state4 $end
$var parameter 6 G state5 $end
$var reg 4 H col [3:0] $end
$var reg 1 2 load_num $end
$var reg 6 I next_state [5:0] $end
$var reg 4 J num [3:0] $end
$var reg 6 K state [5:0] $end
$var reg 1 L sum_row $end
$upscope $end
$scope module Multiplicador $end
$var wire 1 7 clk $end
$var wire 1 & rst $end
$var wire 1 * shift_HQ_LQ_Q_1 $end
$var wire 1 3 load_add $end
$var wire 1 4 load_B $end
$var wire 1 5 load_A $end
$var wire 1 : add_sub $end
$var wire 8 M B [7:0] $end
$var wire 8 N A [7:0] $end
$var parameter 32 O N $end
$var reg 8 P HQ [7:0] $end
$var reg 8 Q LQ [7:0] $end
$var reg 8 R M [7:0] $end
$var reg 1 S Q_1 $end
$var reg 2 T Q_LSB [1:0] $end
$var reg 16 U Y [15:0] $end
$var reg 8 V adder_sub_out [7:0] $end
$var reg 17 W shift [16:0] $end
$upscope $end
$scope module Multiplicandos $end
$var wire 1 $ clk $end
$var wire 1 2 load_num $end
$var wire 4 X num [3:0] $end
$var wire 1 & rst $end
$var parameter 4 Y delete $end
$var parameter 4 Z enter $end
$var parameter 3 [ s0 $end
$var parameter 3 \ s1 $end
$var parameter 3 ] s2 $end
$var parameter 3 ^ s3 $end
$var parameter 3 _ s4 $end
$var parameter 3 ` s5 $end
$var parameter 3 a s6 $end
$var reg 3 b next_state [2:0] $end
$var reg 8 c num_A [7:0] $end
$var reg 8 d num_B [7:0] $end
$var reg 8 e num_o [7:0] $end
$var reg 8 f num_parcial [7:0] $end
$var reg 1 ) signal_num $end
$var reg 3 g state [2:0] $end
$upscope $end
$scope module Segmentos7 $end
$var wire 1 $ clk $end
$var wire 1 2 load_num $end
$var wire 16 h num [15:0] $end
$var parameter 3 i sel0 $end
$var parameter 3 j sel1 $end
$var parameter 3 k sel2 $end
$var parameter 3 l sel3 $end
$var parameter 3 m sel4 $end
$var reg 5 n anodos [4:0] $end
$var reg 4 o digito [3:0] $end
$var reg 4 p next_digito [3:0] $end
$var reg 3 q next_select [2:0] $end
$var reg 7 r segmentos [6:0] $end
$var reg 3 s select [2:0] $end
$upscope $end
$scope module Sync $end
$var wire 1 7 clk_div $end
$var wire 4 t row [3:0] $end
$var wire 1 & rst $end
$var reg 4 u sync_row [3:0] $end
$var reg 4 v val [3:0] $end
$upscope $end
$scope module ctrl $end
$var wire 1 7 clk $end
$var wire 2 w q_LSB [1:0] $end
$var wire 1 & rst $end
$var wire 1 ) signal_num $end
$var parameter 7 x idle $end
$var parameter 7 y init $end
$var parameter 32 z n $end
$var parameter 7 { res $end
$var parameter 7 | sel0 $end
$var parameter 7 } sel1 $end
$var parameter 7 ~ shift $end
$var parameter 7 !" sum $end
$var reg 1 : add_sub $end
$var reg 3 "" cont [2:0] $end
$var reg 1 5 load_A $end
$var reg 1 4 load_B $end
$var reg 1 3 load_add $end
$var reg 7 #" next_state [6:0] $end
$var reg 1 * shift_HQ_LQ_Q_1 $end
$var reg 7 $" state [6:0] $end
$var reg 2 %" z [1:0] $end
$upscope $end
$upscope $end
$upscope $end
$enddefinitions $end
$comment Show the parameter values. $end
$dumpall
b1000 !"
b100000 ~
b1000000 }
b100 |
b10000 {
b1000 z
b10 y
b1 x
b100 m
b11 l
b10 k
b1 j
b0 i
b110 a
b101 `
b100 _
b11 ^
b10 ]
b1 \
b0 [
b1011 Z
b1100 Y
b1000 O
b100000 G
b10000 F
b1000 E
b100 D
b10 C
b1 B
b110100101111000 ?
$end
#0
$dumpvars
b0 %"
bx $"
b1 #"
b111 ""
bx w
b0 v
bx u
b0 t
bx s
b1111111 r
b0 q
bx p
bx o
b0 n
bx h
bx g
bx f
bx e
bx d
bx c
bx b
b0 X
bx W
bx V
bx U
bx T
xS
bx R
bx Q
bx P
bx N
bx M
0L
bx K
b0 J
b1 I
b1111 H
b0 A
b0 @
bx >
bx =
bx <
bx ;
0:
b0 9
bx 8
17
b1111 6
05
04
03
02
b0 1
bx 0
bx /
bx .
bx -
bx ,
b1111111 +
0*
x)
bx (
b0 '
x&
b0 %
0$
b0 #
b1111 "
b1111111 !
$end
#1000
b1 q
b1 #
b1 9
b1 n
b1 @
b1 K
b0 s
1$
#2000
0$
#3000
b10 q
b10 #
b10 9
b10 n
b1 s
b10 @
1$
#4000
0$
#5000
b11 q
b100 #
b100 9
b100 n
b11 @
b10 s
1$
#6000
0$
#7000
b100 q
b1000 #
b1000 9
b1000 n
b11 s
b100 @
1$
#8000
0$
#9000
b0 p
b0 q
b10000 #
b10000 9
b10000 n
b101 @
b100 s
1$
#10000
0$
#11000
b111111 !
b111111 +
b111111 r
bx p
b1 q
b1 #
b1 9
b1 n
b0 o
b0 s
b110 @
1$
#12000
0$
#13000
b1111111 !
b1111111 +
b1111111 r
b10 q
b10 #
b10 9
b10 n
b111 @
bx o
b1 s
1$
#14000
0$
#15000
b11 q
b100 #
b100 9
b100 n
b10 s
b1000 @
1$
#16000
0$
#17000
b100 q
b1000 #
b1000 9
b1000 n
b1001 @
b11 s
1$
#18000
0$
#19000
b0 p
b0 q
b10000 #
b10000 9
b10000 n
b100 s
b1010 @
1$
#20000
0$
#21000
b111111 !
b111111 +
b111111 r
bx p
b1 q
b1 #
b1 9
b1 n
b1011 @
b0 o
b0 s
1$
#22000
0$
#23000
b1111111 !
b1111111 +
b1111111 r
b10 q
b10 #
b10 9
b10 n
bx o
b1 s
b1100 @
1$
#24000
0$
#25000
b11 q
b100 #
b100 9
b100 n
b1101 @
b10 s
1$
#26000
0$
#27000
b100 q
b1000 #
b1000 9
b1000 n
b11 s
b1110 @
1$
#28000
0$
#29000
b0 p
b0 q
b10000 #
b10000 9
b10000 n
b1111 @
b100 s
1$
#30000
0$
#31000
b111111 !
b111111 +
b111111 r
bx p
b1 q
b1 #
b1 9
b1 n
b0 o
b0 s
b10000 @
1$
#32000
0$
#33000
b1111111 !
b1111111 +
b1111111 r
b10 q
b10 #
b10 9
b10 n
b10001 @
bx o
b1 s
1$
#34000
0$
#35000
b11 q
b100 #
b100 9
b100 n
b10 s
b10010 @
1$
#36000
0$
#37000
b100 q
b1000 #
b1000 9
b1000 n
b10011 @
b11 s
1$
#38000
0$
#39000
b0 p
b0 q
b10000 #
b10000 9
b10000 n
b100 s
b10100 @
1$
#40000
0$
#41000
b111111 !
b111111 +
b111111 r
bx p
b1 q
b1 #
b1 9
b1 n
b10101 @
b0 o
b0 s
1$
#42000
0$
#43000
b1111111 !
b1111111 +
b1111111 r
b10 q
b10 #
b10 9
b10 n
bx o
b1 s
b10110 @
1$
#44000
0$
#45000
b11 q
b100 #
b100 9
b100 n
b10111 @
b10 s
1$
#46000
0$
#47000
b100 q
b1000 #
b1000 9
b1000 n
b11 s
b11000 @
1$
#48000
0$
#49000
b0 p
b0 q
b10000 #
b10000 9
b10000 n
b11001 @
b100 s
1$
#50000
0$
#51000
b111111 !
b111111 +
b111111 r
bx p
b1 q
b1 #
b1 9
b1 n
b0 o
b0 s
b11010 @
1$
#52000
0$
#53000
b1111111 !
b1111111 +
b1111111 r
b10 q
b10 #
b10 9
b10 n
b11011 @
bx o
b1 s
1$
#54000
0$
#55000
b11 q
b100 #
b100 9
b100 n
b10 s
b11100 @
1$
#56000
0$
#57000
b100 q
b1000 #
b1000 9
b1000 n
b11101 @
b11 s
1$
#58000
0$
#59000
b0 p
b0 q
b10000 #
b10000 9
b10000 n
b100 s
b11110 @
1$
#60000
0$
#61000
b111111 !
b111111 +
b111111 r
bx p
b1 q
b1 #
b1 9
b1 n
b11111 @
b0 o
b0 s
1$
#62000
0$
#63000
b1111111 !
b1111111 +
b1111111 r
b10 q
b10 #
b10 9
b10 n
bx o
b1 s
b100000 @
1$
#64000
0$
#65000
b11 q
b100 #
b100 9
b100 n
b100001 @
b10 s
1$
#66000
0$
#67000
b100 q
b1000 #
b1000 9
b1000 n
b11 s
b100010 @
1$
#68000
0$
#69000
b0 p
b0 q
b10000 #
b10000 9
b10000 n
b100011 @
b100 s
1$
#70000
0$
#71000
b111111 !
b111111 +
b111111 r
bx p
b1 q
b1 #
b1 9
b1 n
b0 o
b0 s
b100100 @
1$
#72000
0$
#73000
b1111111 !
b1111111 +
b1111111 r
b10 q
b10 #
b10 9
b10 n
b100101 @
bx o
b1 s
1$
#74000
0$
#75000
b11 q
b100 #
b100 9
b100 n
b10 s
b100110 @
1$
#76000
0$
#77000
b100 q
b1000 #
b1000 9
b1000 n
b100111 @
b11 s
1$
#78000
0$
#79000
b0 p
b0 q
b10000 #
b10000 9
b10000 n
b100 s
b101000 @
1$
#80000
0$
#81000
b111111 !
b111111 +
b111111 r
bx p
b1 q
b1 #
b1 9
b1 n
b101001 @
b0 o
b0 s
1$
#82000
0$
#83000
b1111111 !
b1111111 +
b1111111 r
b10 q
b10 #
b10 9
b10 n
bx o
b1 s
b101010 @
1$
#84000
0$
#85000
b11 q
b100 #
b100 9
b100 n
b101011 @
b10 s
1$
#86000
0$
#87000
b100 q
b1000 #
b1000 9
b1000 n
b11 s
b101100 @
1$
#88000
0$
#89000
b0 p
b0 q
b10000 #
b10000 9
b10000 n
b101101 @
b100 s
1$
#90000
0$
#91000
b111111 !
b111111 +
b111111 r
bx p
b1 q
b1 #
b1 9
b1 n
b0 o
b0 s
b101110 @
1$
#92000
0$
#93000
b1111111 !
b1111111 +
b1111111 r
b10 q
b10 #
b10 9
b10 n
b101111 @
bx o
b1 s
1$
#94000
0$
#95000
b11 q
b100 #
b100 9
b100 n
b10 s
b110000 @
1$
#96000
0$
#97000
b100 q
b1000 #
b1000 9
b1000 n
b110001 @
b11 s
1$
#98000
0$
#99000
b0 p
b0 q
b10000 #
b10000 9
b10000 n
b100 s
b110010 @
1$
#100000
b10 I
1L
0$
b10 %
b10 '
b10 A
b10 t
#101000
b111111 !
b111111 +
b111111 r
bx p
b1 q
b1 #
b1 9
b1 n
b110011 @
b10 K
b0 o
b0 s
b10 I
1$
#102000
b100 1
b100 J
b100 X
12
b1 "
b1 6
b1 H
b100000 I
0$
#103000
b1111111 !
b1111111 +
b1111111 r
b10 q
b10 #
b10 9
b10 n
bx o
b1 s
b100000 K
b110100 @
12
b1 "
b1 6
b1 H
b100000 I
1$
#104000
b0 1
b0 J
b0 X
02
b1111 "
b1111 6
b1111 H
b10 I
0$
#105000
b11 q
b100 #
b100 9
b100 n
b110101 @
b10 K
b10 s
b10 I
1$
#106000
b100 1
b100 J
b100 X
12
b1 "
b1 6
b1 H
b100000 I
0$
#107000
b100 q
b1000 #
b1000 9
b1000 n
b11 s
b100000 K
b110110 @
12
b1 "
b1 6
b1 H
b100000 I
1$
#108000
b0 1
b0 J
b0 X
02
b1111 "
b1111 6
b1111 H
b10 I
0$
#109000
b0 p
b0 q
b10000 #
b10000 9
b10000 n
b110111 @
b10 K
b100 s
b10 I
1$
#110000
b100 1
b100 J
b100 X
12
b1 "
b1 6
b1 H
b100000 I
0$
#111000
b111111 !
b111111 +
b111111 r
bx p
b1 q
b1 #
b1 9
b1 n
b0 o
b0 s
b100000 K
b111000 @
12
b1 "
b1 6
b1 H
b100000 I
1$
#112000
b0 1
b0 J
b0 X
02
b1111 "
b1111 6
b1111 H
b10 I
0$
#113000
b1111111 !
b1111111 +
b1111111 r
b10 q
b10 #
b10 9
b10 n
b111001 @
b10 K
bx o
b1 s
b10 I
1$
#114000
b100 1
b100 J
b100 X
12
b1 "
b1 6
b1 H
b100000 I
0$
#115000
b11 q
b100 #
b100 9
b100 n
b10 s
b100000 K
b111010 @
12
b1 "
b1 6
b1 H
b100000 I
1$
#116000
b0 1
b0 J
b0 X
02
b1111 "
b1111 6
b1111 H
b10 I
0$
#117000
b100 q
b1000 #
b1000 9
b1000 n
b111011 @
b10 K
b11 s
b10 I
1$
#118000
b100 1
b100 J
b100 X
12
b1 "
b1 6
b1 H
b100000 I
0$
#119000
b0 p
b0 q
b10000 #
b10000 9
b10000 n
b100 s
b100000 K
b111100 @
12
b1 "
b1 6
b1 H
b100000 I
1$
#120000
b0 1
b0 J
b0 X
02
b1111 "
b1111 6
b1111 H
b10 I
0$
#121000
b111111 !
b111111 +
b111111 r
bx p
b1 q
b1 #
b1 9
b1 n
b111101 @
b10 K
b0 o
b0 s
b10 I
1$
